{"result":"success","data":[{"route_id":"003","start_time":"06:35:00","start_stop_name":"LIGEA  CAPOLINEA","finish_time":"07:04:00","finish_stop_name":"OSPEDALE DA PROCIDA","trip_id":"52_818620"},{"route_id":"003","start_time":"07:45:00","start_stop_name":"LIGEA  CAPOLINEA","finish_time":"08:14:00","finish_stop_name":"OSPEDALE DA PROCIDA","trip_id":"52_815273"},{"route_id":"003","start_time":"08:45:00","start_stop_name":"LIGEA  CAPOLINEA","finish_time":"09:14:00","finish_stop_name":"OSPEDALE DA PROCIDA","trip_id":"52_815274"},{"route_id":"003","start_time":"09:45:00","start_stop_name":"LIGEA  CAPOLINEA","finish_time":"10:16:00","finish_stop_name":"OSPEDALE DA PROCIDA","trip_id":"52_815275"},{"route_id":"003","start_time":"10:45:00","start_stop_name":"LIGEA  CAPOLINEA","finish_time":"11:16:00","finish_stop_name":"OSPEDALE DA PROCIDA","trip_id":"52_815276"},{"route_id":"003","start_time":"11:45:00","start_stop_name":"LIGEA  CAPOLINEA","finish_time":"12:16:00","finish_stop_name":"OSPEDALE DA PROCIDA","trip_id":"52_815277"},{"route_id":"003","start_time":"12:45:00","start_stop_name":"LIGEA  CAPOLINEA","finish_time":"13:14:00","finish_stop_name":"OSPEDALE DA PROCIDA","trip_id":"52_815278"},{"route_id":"003","start_time":"13:50:00","start_stop_name":"LIGEA  CAPOLINEA","finish_time":"14:18:00","finish_stop_name":"OSPEDALE DA PROCIDA","trip_id":"52_815279"},{"route_id":"003","start_time":"14:50:00","start_stop_name":"LIGEA  CAPOLINEA","finish_time":"15:17:00","finish_stop_name":"OSPEDALE DA PROCIDA","trip_id":"52_815280"},{"route_id":"003","start_time":"15:45:00","start_stop_name":"LIGEA  CAPOLINEA","finish_time":"16:12:00","finish_stop_name":"OSPEDALE DA PROCIDA","trip_id":"52_815281"},{"route_id":"003","start_time":"16:45:00","start_stop_name":"LIGEA  CAPOLINEA","finish_time":"17:13:00","finish_stop_name":"OSPEDALE DA PROCIDA","trip_id":"52_815282"},{"route_id":"003","start_time":"17:45:00","start_stop_name":"LIGEA  CAPOLINEA","finish_time":"18:13:00","finish_stop_name":"OSPEDALE DA PROCIDA","trip_id":"52_815283"},{"route_id":"003","start_time":"18:45:00","start_stop_name":"LIGEA  CAPOLINEA","finish_time":"19:13:00","finish_stop_name":"OSPEDALE DA PROCIDA","trip_id":"52_815284"},{"route_id":"003","start_time":"19:45:00","start_stop_name":"LIGEA  CAPOLINEA","finish_time":"20:13:00","finish_stop_name":"OSPEDALE DA PROCIDA","trip_id":"52_815285"},{"route_id":"003","start_time":"20:50:00","start_stop_name":"LIGEA  CAPOLINEA","finish_time":"21:15:00","finish_stop_name":"OSPEDALE DA PROCIDA","trip_id":"52_815286"},{"route_id":"003","start_time":"06:15:00","start_stop_name":"SERIPANDO (CAP.)","finish_time":"06:33:00","finish_stop_name":"LIGEA  CAPOLINEA","trip_id":"52_815303"},{"route_id":"003","start_time":"07:05:00","start_stop_name":"OSPEDALE DA PROCIDA","finish_time":"07:23:00","finish_stop_name":"LIGEA  CAPOLINEA","trip_id":"52_815288"},{"route_id":"003","start_time":"08:15:00","start_stop_name":"OSPEDALE DA PROCIDA","finish_time":"08:37:00","finish_stop_name":"LIGEA  CAPOLINEA","trip_id":"52_815289"},{"route_id":"003","start_time":"09:15:00","start_stop_name":"OSPEDALE DA PROCIDA","finish_time":"09:38:00","finish_stop_name":"LIGEA  CAPOLINEA","trip_id":"52_815290"},{"route_id":"003","start_time":"10:16:00","start_stop_name":"OSPEDALE DA PROCIDA","finish_time":"10:39:00","finish_stop_name":"LIGEA  CAPOLINEA","trip_id":"52_815291"},{"route_id":"003","start_time":"11:16:00","start_stop_name":"OSPEDALE DA PROCIDA","finish_time":"11:39:00","finish_stop_name":"LIGEA  CAPOLINEA","trip_id":"52_815292"},{"route_id":"003","start_time":"12:16:00","start_stop_name":"OSPEDALE DA PROCIDA","finish_time":"12:39:00","finish_stop_name":"LIGEA  CAPOLINEA","trip_id":"52_815293"},{"route_id":"003","start_time":"13:15:00","start_stop_name":"OSPEDALE DA PROCIDA","finish_time":"13:37:00","finish_stop_name":"LIGEA  CAPOLINEA","trip_id":"52_815294"},{"route_id":"003","start_time":"14:20:00","start_stop_name":"OSPEDALE DA PROCIDA","finish_time":"14:41:00","finish_stop_name":"LIGEA  CAPOLINEA","trip_id":"52_815295"},{"route_id":"003","start_time":"15:17:00","start_stop_name":"OSPEDALE DA PROCIDA","finish_time":"15:39:00","finish_stop_name":"LIGEA  CAPOLINEA","trip_id":"52_815296"},{"route_id":"003","start_time":"16:15:00","start_stop_name":"OSPEDALE DA PROCIDA","finish_time":"16:37:00","finish_stop_name":"LIGEA  CAPOLINEA","trip_id":"52_815297"},{"route_id":"003","start_time":"17:15:00","start_stop_name":"OSPEDALE DA PROCIDA","finish_time":"17:37:00","finish_stop_name":"LIGEA  CAPOLINEA","trip_id":"52_815298"},{"route_id":"003","start_time":"18:15:00","start_stop_name":"OSPEDALE DA PROCIDA","finish_time":"18:37:00","finish_stop_name":"LIGEA  CAPOLINEA","trip_id":"52_815299"},{"route_id":"003","start_time":"19:15:00","start_stop_name":"OSPEDALE DA PROCIDA","finish_time":"19:35:00","finish_stop_name":"LIGEA  CAPOLINEA","trip_id":"52_815300"},{"route_id":"003","start_time":"20:15:00","start_stop_name":"OSPEDALE DA PROCIDA","finish_time":"20:34:00","finish_stop_name":"LIGEA  CAPOLINEA","trip_id":"52_815301"},{"route_id":"003","start_time":"21:15:00","start_stop_name":"OSPEDALE DA PROCIDA","finish_time":"21:23:00","finish_stop_name":"CONCORDIA","trip_id":"52_815302"},{"route_id":"008","start_time":"05:15:00","start_stop_name":"VINCIPROVA","finish_time":"06:05:00","finish_stop_name":"BATTIPAGLIA (CAP.)","trip_id":"52_819089"},{"route_id":"008","start_time":"05:40:00","start_stop_name":"VINCIPROVA","finish_time":"06:40:00","finish_stop_name":"BATTIPAGLIA (CAP.)","trip_id":"52_819090"},{"route_id":"008","start_time":"06:20:00","start_stop_name":"VINCIPROVA","finish_time":"07:12:00","finish_stop_name":"BATTIPAGLIA (CAP.)","trip_id":"52_819091"},{"route_id":"008","start_time":"07:00:00","start_stop_name":"VINCIPROVA","finish_time":"08:10:00","finish_stop_name":"BATTIPAGLIA (CAP.)","trip_id":"52_819092"},{"route_id":"008","start_time":"07:40:00","start_stop_name":"VINCIPROVA","finish_time":"08:50:00","finish_stop_name":"BATTIPAGLIA (CAP.)","trip_id":"52_819093"},{"route_id":"008","start_time":"08:20:00","start_stop_name":"VINCIPROVA","finish_time":"09:30:00","finish_stop_name":"BATTIPAGLIA (CAP.)","trip_id":"52_819094"},{"route_id":"008","start_time":"09:00:00","start_stop_name":"VINCIPROVA","finish_time":"10:10:00","finish_stop_name":"BATTIPAGLIA (CAP.)","trip_id":"52_819095"},{"route_id":"008","start_time":"09:40:00","start_stop_name":"VINCIPROVA","finish_time":"10:50:00","finish_stop_name":"BATTIPAGLIA (CAP.)","trip_id":"52_819096"},{"route_id":"008","start_time":"10:20:00","start_stop_name":"VINCIPROVA","finish_time":"11:30:00","finish_stop_name":"BATTIPAGLIA (CAP.)","trip_id":"52_819115"},{"route_id":"008","start_time":"11:00:00","start_stop_name":"VINCIPROVA","finish_time":"12:10:00","finish_stop_name":"BATTIPAGLIA (CAP.)","trip_id":"52_819116"},{"route_id":"008","start_time":"11:40:00","start_stop_name":"VINCIPROVA","finish_time":"12:50:00","finish_stop_name":"BATTIPAGLIA (CAP.)","trip_id":"52_819099"},{"route_id":"008","start_time":"12:20:00","start_stop_name":"VINCIPROVA","finish_time":"13:30:00","finish_stop_name":"BATTIPAGLIA (CAP.)","trip_id":"52_819100"},{"route_id":"008","start_time":"13:00:00","start_stop_name":"VINCIPROVA","finish_time":"14:10:00","finish_stop_name":"BATTIPAGLIA (CAP.)","trip_id":"52_819101"},{"route_id":"008","start_time":"13:40:00","start_stop_name":"VINCIPROVA","finish_time":"14:50:00","finish_stop_name":"BATTIPAGLIA (CAP.)","trip_id":"52_819102"},{"route_id":"008","start_time":"14:20:00","start_stop_name":"VINCIPROVA","finish_time":"15:30:00","finish_stop_name":"BATTIPAGLIA (CAP.)","trip_id":"52_819103"},{"route_id":"008","start_time":"15:00:00","start_stop_name":"VINCIPROVA","finish_time":"16:10:00","finish_stop_name":"BATTIPAGLIA (CAP.)","trip_id":"52_819104"},{"route_id":"008","start_time":"15:40:00","start_stop_name":"VINCIPROVA","finish_time":"16:50:00","finish_stop_name":"BATTIPAGLIA (CAP.)","trip_id":"52_819105"},{"route_id":"008","start_time":"16:20:00","start_stop_name":"VINCIPROVA","finish_time":"17:30:00","finish_stop_name":"BATTIPAGLIA (CAP.)","trip_id":"52_819119"},{"route_id":"008","start_time":"17:00:00","start_stop_name":"VINCIPROVA","finish_time":"18:10:00","finish_stop_name":"BATTIPAGLIA (CAP.)","trip_id":"52_819107"},{"route_id":"008","start_time":"17:40:00","start_stop_name":"VINCIPROVA","finish_time":"18:50:00","finish_stop_name":"BATTIPAGLIA (CAP.)","trip_id":"52_819121"},{"route_id":"008","start_time":"18:20:00","start_stop_name":"VINCIPROVA","finish_time":"19:30:00","finish_stop_name":"BATTIPAGLIA (CAP.)","trip_id":"52_819108"},{"route_id":"008","start_time":"19:00:00","start_stop_name":"VINCIPROVA","finish_time":"20:10:00","finish_stop_name":"BATTIPAGLIA (CAP.)","trip_id":"52_819109"},{"route_id":"008","start_time":"19:40:00","start_stop_name":"VINCIPROVA","finish_time":"20:50:00","finish_stop_name":"BATTIPAGLIA (CAP.)","trip_id":"52_819110"},{"route_id":"008","start_time":"20:20:00","start_stop_name":"VINCIPROVA","finish_time":"21:30:00","finish_stop_name":"BATTIPAGLIA (CAP.)","trip_id":"52_819111"},{"route_id":"008","start_time":"21:00:00","start_stop_name":"VINCIPROVA","finish_time":"22:08:00","finish_stop_name":"BATTIPAGLIA (CAP.)","trip_id":"52_819112"},{"route_id":"008","start_time":"21:40:00","start_stop_name":"VINCIPROVA","finish_time":"22:40:00","finish_stop_name":"BATTIPAGLIA (CAP.)","trip_id":"52_819113"},{"route_id":"008","start_time":"22:40:00","start_stop_name":"VINCIPROVA","finish_time":"23:30:00","finish_stop_name":"BATTIPAGLIA (CAP.)","trip_id":"52_819114"},{"route_id":"008","start_time":"05:15:00","start_stop_name":"BATTIPAGLIA (CAP.)","finish_time":"06:08:00","finish_stop_name":"VINCIPROVA","trip_id":"52_819124"},{"route_id":"008","start_time":"05:40:00","start_stop_name":"BATTIPAGLIA (CAP.)","finish_time":"06:33:00","finish_stop_name":"VINCIPROVA","trip_id":"52_819125"},{"route_id":"008","start_time":"06:10:00","start_stop_name":"BATTIPAGLIA (CAP.)","finish_time":"07:15:00","finish_stop_name":"VINCIPROVA","trip_id":"52_819126"},{"route_id":"008","start_time":"06:40:00","start_stop_name":"BATTIPAGLIA (CAP.)","finish_time":"07:58:00","finish_stop_name":"VINCIPROVA","trip_id":"52_819127"},{"route_id":"008","start_time":"07:25:00","start_stop_name":"BATTIPAGLIA (CAP.)","finish_time":"08:40:00","finish_stop_name":"VINCIPROVA","trip_id":"52_819128"},{"route_id":"008","start_time":"08:10:00","start_stop_name":"BATTIPAGLIA (CAP.)","finish_time":"09:30:00","finish_stop_name":"VINCIPROVA","trip_id":"52_819129"},{"route_id":"008","start_time":"08:50:00","start_stop_name":"BATTIPAGLIA (CAP.)","finish_time":"10:10:00","finish_stop_name":"VINCIPROVA","trip_id":"52_819130"},{"route_id":"008","start_time":"09:30:00","start_stop_name":"BATTIPAGLIA (CAP.)","finish_time":"10:57:00","finish_stop_name":"VINCIPROVA","trip_id":"52_819131"},{"route_id":"008","start_time":"10:10:00","start_stop_name":"BATTIPAGLIA (CAP.)","finish_time":"11:31:00","finish_stop_name":"VINCIPROVA","trip_id":"52_819157"},{"route_id":"008","start_time":"10:50:00","start_stop_name":"BATTIPAGLIA (CAP.)","finish_time":"12:11:00","finish_stop_name":"VINCIPROVA","trip_id":"52_819158"},{"route_id":"008","start_time":"11:30:00","start_stop_name":"BATTIPAGLIA (CAP.)","finish_time":"12:57:00","finish_stop_name":"VINCIPROVA","trip_id":"52_819133"},{"route_id":"008","start_time":"12:10:00","start_stop_name":"BATTIPAGLIA (CAP.)","finish_time":"13:32:00","finish_stop_name":"VINCIPROVA","trip_id":"52_819134"},{"route_id":"008","start_time":"12:50:00","start_stop_name":"BATTIPAGLIA (CAP.)","finish_time":"14:10:00","finish_stop_name":"VINCIPROVA","trip_id":"52_819135"},{"route_id":"008","start_time":"13:30:00","start_stop_name":"BATTIPAGLIA (CAP.)","finish_time":"14:47:00","finish_stop_name":"VINCIPROVA","trip_id":"52_819136"},{"route_id":"008","start_time":"14:10:00","start_stop_name":"BATTIPAGLIA (CAP.)","finish_time":"15:27:00","finish_stop_name":"VINCIPROVA","trip_id":"52_819137"},{"route_id":"008","start_time":"14:50:00","start_stop_name":"BATTIPAGLIA (CAP.)","finish_time":"16:07:00","finish_stop_name":"VINCIPROVA","trip_id":"52_819138"},{"route_id":"008","start_time":"15:30:00","start_stop_name":"BATTIPAGLIA (CAP.)","finish_time":"16:44:00","finish_stop_name":"VINCIPROVA","trip_id":"52_819160"},{"route_id":"008","start_time":"16:10:00","start_stop_name":"BATTIPAGLIA (CAP.)","finish_time":"17:37:00","finish_stop_name":"VINCIPROVA","trip_id":"52_819140"},{"route_id":"008","start_time":"16:50:00","start_stop_name":"BATTIPAGLIA (CAP.)","finish_time":"18:14:00","finish_stop_name":"VINCIPROVA","trip_id":"52_819161"},{"route_id":"008","start_time":"17:30:00","start_stop_name":"BATTIPAGLIA (CAP.)","finish_time":"18:57:00","finish_stop_name":"VINCIPROVA","trip_id":"52_819142"},{"route_id":"008","start_time":"18:10:00","start_stop_name":"BATTIPAGLIA (CAP.)","finish_time":"19:37:00","finish_stop_name":"VINCIPROVA","trip_id":"52_819143"},{"route_id":"008","start_time":"18:50:00","start_stop_name":"BATTIPAGLIA (CAP.)","finish_time":"20:17:00","finish_stop_name":"VINCIPROVA","trip_id":"52_819144"},{"route_id":"008","start_time":"19:30:00","start_stop_name":"BATTIPAGLIA (CAP.)","finish_time":"20:56:00","finish_stop_name":"VINCIPROVA","trip_id":"52_819145"},{"route_id":"008","start_time":"20:10:00","start_stop_name":"BATTIPAGLIA (CAP.)","finish_time":"21:21:00","finish_stop_name":"VINCIPROVA","trip_id":"52_819146"},{"route_id":"008","start_time":"20:50:00","start_stop_name":"BATTIPAGLIA (CAP.)","finish_time":"21:56:00","finish_stop_name":"VINCIPROVA","trip_id":"52_819147"},{"route_id":"008","start_time":"21:30:00","start_stop_name":"BATTIPAGLIA (CAP.)","finish_time":"22:35:00","finish_stop_name":"VINCIPROVA","trip_id":"52_819148"},{"route_id":"008","start_time":"22:10:00","start_stop_name":"BATTIPAGLIA (CAP.)","finish_time":"23:15:00","finish_stop_name":"VINCIPROVA","trip_id":"52_819150"},{"route_id":"008","start_time":"22:40:00","start_stop_name":"BATTIPAGLIA (CAP.)","finish_time":"23:45:00","finish_stop_name":"VINCIPROVA","trip_id":"52_819151"},{"route_id":"008","start_time":"23:30:00","start_stop_name":"BATTIPAGLIA (CAP.)","finish_time":"00:25:00","finish_stop_name":"VINCIPROVA","trip_id":"52_819153"},{"route_id":"015","start_time":"06:35:00","start_stop_name":"VINCIPROVA","finish_time":"07:00:00","finish_stop_name":"CASA MANZO - CAPOLINEA","trip_id":"52_818743"},{"route_id":"015","start_time":"07:35:00","start_stop_name":"VINCIPROVA","finish_time":"08:05:00","finish_stop_name":"CASA MANZO - CAPOLINEA","trip_id":"52_818744"},{"route_id":"015","start_time":"08:35:00","start_stop_name":"VINCIPROVA","finish_time":"09:05:00","finish_stop_name":"CASA MANZO - CAPOLINEA","trip_id":"52_818746"},{"route_id":"015","start_time":"09:35:00","start_stop_name":"VINCIPROVA","finish_time":"10:05:00","finish_stop_name":"CASA MANZO - CAPOLINEA","trip_id":"52_818747"},{"route_id":"015","start_time":"10:35:00","start_stop_name":"VINCIPROVA","finish_time":"11:05:00","finish_stop_name":"CASA MANZO - CAPOLINEA","trip_id":"52_818749"},{"route_id":"015","start_time":"11:35:00","start_stop_name":"VINCIPROVA","finish_time":"12:05:00","finish_stop_name":"CASA MANZO - CAPOLINEA","trip_id":"52_818750"},{"route_id":"015","start_time":"12:35:00","start_stop_name":"VINCIPROVA","finish_time":"13:05:00","finish_stop_name":"CASA MANZO - CAPOLINEA","trip_id":"52_818752"},{"route_id":"015","start_time":"13:35:00","start_stop_name":"VINCIPROVA","finish_time":"14:05:00","finish_stop_name":"CASA MANZO - CAPOLINEA","trip_id":"52_818753"},{"route_id":"015","start_time":"14:35:00","start_stop_name":"VINCIPROVA","finish_time":"15:05:00","finish_stop_name":"CASA MANZO - CAPOLINEA","trip_id":"52_818755"},{"route_id":"015","start_time":"15:35:00","start_stop_name":"VINCIPROVA","finish_time":"16:05:00","finish_stop_name":"CASA MANZO - CAPOLINEA","trip_id":"52_818756"},{"route_id":"015","start_time":"16:35:00","start_stop_name":"VINCIPROVA","finish_time":"17:05:00","finish_stop_name":"CASA MANZO - CAPOLINEA","trip_id":"52_818757"},{"route_id":"015","start_time":"17:35:00","start_stop_name":"VINCIPROVA","finish_time":"18:05:00","finish_stop_name":"CASA MANZO - CAPOLINEA","trip_id":"52_818758"},{"route_id":"015","start_time":"18:35:00","start_stop_name":"VINCIPROVA","finish_time":"19:05:00","finish_stop_name":"CASA MANZO - CAPOLINEA","trip_id":"52_818759"},{"route_id":"015","start_time":"19:35:00","start_stop_name":"VINCIPROVA","finish_time":"20:05:00","finish_stop_name":"CASA MANZO - CAPOLINEA","trip_id":"52_818760"},{"route_id":"015","start_time":"20:35:00","start_stop_name":"VINCIPROVA","finish_time":"21:05:00","finish_stop_name":"CASA MANZO - CAPOLINEA","trip_id":"52_818761"},{"route_id":"015","start_time":"21:50:00","start_stop_name":"VINCIPROVA","finish_time":"22:15:00","finish_stop_name":"CASA MANZO - CAPOLINEA","trip_id":"52_818762"},{"route_id":"015","start_time":"09:05:00","start_stop_name":"CASA MANZO - CAPOLINEA","finish_time":"09:23:00","finish_stop_name":"VINCIPROVA","trip_id":"52_818763"},{"route_id":"015","start_time":"10:05:00","start_stop_name":"CASA MANZO - CAPOLINEA","finish_time":"10:23:00","finish_stop_name":"VINCIPROVA","trip_id":"52_818764"},{"route_id":"015","start_time":"11:05:00","start_stop_name":"CASA MANZO - CAPOLINEA","finish_time":"11:23:00","finish_stop_name":"VINCIPROVA","trip_id":"52_818766"},{"route_id":"015","start_time":"12:05:00","start_stop_name":"CASA MANZO - CAPOLINEA","finish_time":"12:23:00","finish_stop_name":"VINCIPROVA","trip_id":"52_818767"},{"route_id":"015","start_time":"13:05:00","start_stop_name":"CASA MANZO - CAPOLINEA","finish_time":"13:23:00","finish_stop_name":"VINCIPROVA","trip_id":"52_818769"},{"route_id":"015","start_time":"14:05:00","start_stop_name":"CASA MANZO - CAPOLINEA","finish_time":"14:23:00","finish_stop_name":"VINCIPROVA","trip_id":"52_818770"},{"route_id":"015","start_time":"15:05:00","start_stop_name":"CASA MANZO - CAPOLINEA","finish_time":"15:23:00","finish_stop_name":"VINCIPROVA","trip_id":"52_818771"},{"route_id":"015","start_time":"16:05:00","start_stop_name":"CASA MANZO - CAPOLINEA","finish_time":"16:23:00","finish_stop_name":"VINCIPROVA","trip_id":"52_818772"},{"route_id":"015","start_time":"17:05:00","start_stop_name":"CASA MANZO - CAPOLINEA","finish_time":"17:23:00","finish_stop_name":"VINCIPROVA","trip_id":"52_818773"},{"route_id":"015","start_time":"18:05:00","start_stop_name":"CASA MANZO - CAPOLINEA","finish_time":"18:23:00","finish_stop_name":"VINCIPROVA","trip_id":"52_818774"},{"route_id":"015","start_time":"19:05:00","start_stop_name":"CASA MANZO - CAPOLINEA","finish_time":"19:23:00","finish_stop_name":"VINCIPROVA","trip_id":"52_818775"},{"route_id":"015","start_time":"20:05:00","start_stop_name":"CASA MANZO - CAPOLINEA","finish_time":"20:23:00","finish_stop_name":"VINCIPROVA","trip_id":"52_818776"},{"route_id":"015","start_time":"21:05:00","start_stop_name":"CASA MANZO - CAPOLINEA","finish_time":"21:23:00","finish_stop_name":"VINCIPROVA","trip_id":"52_818777"},{"route_id":"015","start_time":"22:40:00","start_stop_name":"CASA MANZO - CAPOLINEA","finish_time":"22:58:00","finish_stop_name":"VINCIPROVA","trip_id":"52_818778"},{"route_id":"018","start_time":"06:10:00","start_stop_name":"FRATTE","finish_time":"06:21:00","finish_stop_name":"MATIERNO (CAPOLINEA)","trip_id":"52_815305"},{"route_id":"018","start_time":"06:20:00","start_stop_name":"FRATTE","finish_time":"06:26:00","finish_stop_name":"CAPPELLE SUPERIORI","trip_id":"52_815315"},{"route_id":"018","start_time":"07:05:00","start_stop_name":"XXIV MAGGIO  (in salita)","finish_time":"07:17:00","finish_stop_name":"CAPPELLE SUPERIORI","trip_id":"52_815317"},{"route_id":"018","start_time":"07:05:00","start_stop_name":"LIGEA  CAPOLINEA","finish_time":"07:35:00","finish_stop_name":"MATIERNO (CAPOLINEA)","trip_id":"52_815306"},{"route_id":"018","start_time":"08:05:00","start_stop_name":"LIGEA  CAPOLINEA","finish_time":"08:36:00","finish_stop_name":"CAPPELLE SUPERIORI","trip_id":"52_815320"},{"route_id":"018","start_time":"08:30:00","start_stop_name":"LIGEA  CAPOLINEA","finish_time":"09:07:00","finish_stop_name":"MATIERNO (CAPOLINEA)","trip_id":"52_815307"},{"route_id":"018","start_time":"09:25:00","start_stop_name":"LIGEA  CAPOLINEA","finish_time":"10:03:00","finish_stop_name":"MATIERNO (CAPOLINEA)","trip_id":"52_815321"},{"route_id":"018","start_time":"10:45:00","start_stop_name":"LIGEA  CAPOLINEA","finish_time":"11:23:00","finish_stop_name":"MATIERNO (CAPOLINEA)","trip_id":"52_815322"},{"route_id":"018","start_time":"12:15:00","start_stop_name":"LIGEA  CAPOLINEA","finish_time":"12:51:00","finish_stop_name":"MATIERNO (CAPOLINEA)","trip_id":"52_815323"},{"route_id":"018","start_time":"13:00:00","start_stop_name":"LIGEA  CAPOLINEA","finish_time":"13:34:00","finish_stop_name":"MATIERNO (CAPOLINEA)","trip_id":"52_815308"},{"route_id":"018","start_time":"13:45:00","start_stop_name":"LIGEA  CAPOLINEA","finish_time":"14:18:00","finish_stop_name":"MATIERNO (CAPOLINEA)","trip_id":"52_815324"},{"route_id":"018","start_time":"14:30:00","start_stop_name":"LIGEA  CAPOLINEA","finish_time":"15:03:00","finish_stop_name":"MATIERNO (CAPOLINEA)","trip_id":"52_815309"},{"route_id":"018","start_time":"15:10:00","start_stop_name":"LIGEA  CAPOLINEA","finish_time":"15:43:00","finish_stop_name":"MATIERNO (CAPOLINEA)","trip_id":"52_815325"},{"route_id":"018","start_time":"16:20:00","start_stop_name":"LIGEA  CAPOLINEA","finish_time":"16:53:00","finish_stop_name":"MATIERNO (CAPOLINEA)","trip_id":"52_815326"},{"route_id":"018","start_time":"17:50:00","start_stop_name":"LIGEA  CAPOLINEA","finish_time":"18:25:00","finish_stop_name":"MATIERNO (CAPOLINEA)","trip_id":"52_815327"},{"route_id":"018","start_time":"19:20:00","start_stop_name":"LIGEA  CAPOLINEA","finish_time":"19:55:00","finish_stop_name":"MATIERNO (CAPOLINEA)","trip_id":"52_815328"},{"route_id":"018","start_time":"20:50:00","start_stop_name":"LIGEA  CAPOLINEA","finish_time":"21:22:00","finish_stop_name":"MATIERNO (CAPOLINEA)","trip_id":"52_815329"},{"route_id":"018","start_time":"22:00:00","start_stop_name":"LIGEA  CAPOLINEA","finish_time":"22:28:00","finish_stop_name":"MATIERNO (CAPOLINEA)","trip_id":"52_815330"},{"route_id":"018","start_time":"06:30:00","start_stop_name":"MATIERNO (CAPOLINEA)","finish_time":"06:53:00","finish_stop_name":"LIGEA  CAPOLINEA","trip_id":"52_815310"},{"route_id":"018","start_time":"06:35:00","start_stop_name":"CAPPELLE SUPERIORI","finish_time":"06:51:00","finish_stop_name":"XXIV MAGGIO","trip_id":"52_815316"},{"route_id":"018","start_time":"07:25:00","start_stop_name":"CAPPELLE SUPERIORI","finish_time":"07:55:00","finish_stop_name":"LIGEA  CAPOLINEA","trip_id":"52_815318"},{"route_id":"018","start_time":"07:40:00","start_stop_name":"MATIERNO (CAPOLINEA)","finish_time":"08:08:00","finish_stop_name":"LIGEA  CAPOLINEA","trip_id":"52_815311"},{"route_id":"018","start_time":"08:36:00","start_stop_name":"CAPPELLE SUPERIORI","finish_time":"09:07:00","finish_stop_name":"LIGEA  CAPOLINEA","trip_id":"52_815319"},{"route_id":"018","start_time":"09:07:00","start_stop_name":"MATIERNO (CAPOLINEA)","finish_time":"09:35:00","finish_stop_name":"LIGEA  CAPOLINEA","trip_id":"52_815312"},{"route_id":"018","start_time":"10:03:00","start_stop_name":"MATIERNO (CAPOLINEA)","finish_time":"10:32:00","finish_stop_name":"LIGEA  CAPOLINEA","trip_id":"52_815331"},{"route_id":"018","start_time":"11:23:00","start_stop_name":"MATIERNO (CAPOLINEA)","finish_time":"11:51:00","finish_stop_name":"LIGEA  CAPOLINEA","trip_id":"52_815332"},{"route_id":"018","start_time":"12:51:00","start_stop_name":"MATIERNO (CAPOLINEA)","finish_time":"13:18:00","finish_stop_name":"LIGEA  CAPOLINEA","trip_id":"52_815333"},{"route_id":"018","start_time":"13:35:00","start_stop_name":"MATIERNO (CAPOLINEA)","finish_time":"14:02:00","finish_stop_name":"LIGEA  CAPOLINEA","trip_id":"52_815313"},{"route_id":"018","start_time":"14:20:00","start_stop_name":"MATIERNO (CAPOLINEA)","finish_time":"14:47:00","finish_stop_name":"LIGEA  CAPOLINEA","trip_id":"52_815334"},{"route_id":"018","start_time":"15:05:00","start_stop_name":"MATIERNO (CAPOLINEA)","finish_time":"15:32:00","finish_stop_name":"LIGEA  CAPOLINEA","trip_id":"52_815314"},{"route_id":"018","start_time":"15:45:00","start_stop_name":"MATIERNO (CAPOLINEA)","finish_time":"16:12:00","finish_stop_name":"LIGEA  CAPOLINEA","trip_id":"52_815335"},{"route_id":"018","start_time":"16:55:00","start_stop_name":"MATIERNO (CAPOLINEA)","finish_time":"17:22:00","finish_stop_name":"LIGEA  CAPOLINEA","trip_id":"52_815336"},{"route_id":"018","start_time":"18:25:00","start_stop_name":"MATIERNO (CAPOLINEA)","finish_time":"18:52:00","finish_stop_name":"LIGEA  CAPOLINEA","trip_id":"52_815337"},{"route_id":"018","start_time":"19:55:00","start_stop_name":"MATIERNO (CAPOLINEA)","finish_time":"20:22:00","finish_stop_name":"LIGEA  CAPOLINEA","trip_id":"52_815338"},{"route_id":"018","start_time":"21:25:00","start_stop_name":"MATIERNO (CAPOLINEA)","finish_time":"21:48:00","finish_stop_name":"LIGEA  CAPOLINEA","trip_id":"52_815339"},{"route_id":"024","start_time":"06:35:00","start_stop_name":"VINCIPROVA","finish_time":"07:26:00","finish_stop_name":"CAMPOLONGO-CAPOLINEA OSPEDALE","trip_id":"52_819357"},{"route_id":"024","start_time":"08:55:00","start_stop_name":"VINCIPROVA","finish_time":"09:50:00","finish_stop_name":"CAMPOLONGO-CAPOLINEA OSPEDALE","trip_id":"52_819358"},{"route_id":"024","start_time":"13:05:00","start_stop_name":"VINCIPROVA","finish_time":"14:00:00","finish_stop_name":"CAMPOLONGO-CAPOLINEA OSPEDALE","trip_id":"52_819359"},{"route_id":"024","start_time":"15:55:00","start_stop_name":"VINCIPROVA","finish_time":"16:49:00","finish_stop_name":"CAMPOLONGO-CAPOLINEA OSPEDALE","trip_id":"52_819360"},{"route_id":"024","start_time":"19:55:00","start_stop_name":"VINCIPROVA","finish_time":"20:50:00","finish_stop_name":"CAMPOLONGO-CAPOLINEA OSPEDALE","trip_id":"52_819361"},{"route_id":"024","start_time":"07:30:00","start_stop_name":"CAMPOLONGO-CAPOLINEA OSPEDALE","finish_time":"08:38:00","finish_stop_name":"VINCIPROVA","trip_id":"52_819363"},{"route_id":"024","start_time":"10:10:00","start_stop_name":"CAMPOLONGO-CAPOLINEA OSPEDALE","finish_time":"11:08:00","finish_stop_name":"VINCIPROVA","trip_id":"52_819364"},{"route_id":"024","start_time":"14:10:00","start_stop_name":"CAMPOLONGO-CAPOLINEA OSPEDALE","finish_time":"15:08:00","finish_stop_name":"VINCIPROVA","trip_id":"52_819365"},{"route_id":"024","start_time":"17:10:00","start_stop_name":"CAMPOLONGO-CAPOLINEA OSPEDALE","finish_time":"18:08:00","finish_stop_name":"VINCIPROVA","trip_id":"52_819366"},{"route_id":"024","start_time":"21:10:00","start_stop_name":"CAMPOLONGO-CAPOLINEA OSPEDALE","finish_time":"22:03:00","finish_stop_name":"VINCIPROVA","trip_id":"52_819367"},{"route_id":"025","start_time":"06:35:00","start_stop_name":"VINCIPROVA","finish_time":"07:12:00","finish_stop_name":"MONTICELLI - CAPOLINEA","trip_id":"52_818831"},{"route_id":"025","start_time":"07:10:00","start_stop_name":"VINCIPROVA","finish_time":"07:50:00","finish_stop_name":"MONTICELLI - CAPOLINEA","trip_id":"52_818822"},{"route_id":"025","start_time":"07:55:00","start_stop_name":"VINCIPROVA","finish_time":"08:35:00","finish_stop_name":"MONTICELLI - CAPOLINEA","trip_id":"52_818823"},{"route_id":"025","start_time":"08:45:00","start_stop_name":"VINCIPROVA","finish_time":"09:23:00","finish_stop_name":"MONTICELLI - CAPOLINEA","trip_id":"52_818832"},{"route_id":"025","start_time":"09:25:00","start_stop_name":"VINCIPROVA","finish_time":"10:04:00","finish_stop_name":"MONTICELLI - CAPOLINEA","trip_id":"52_818824"},{"route_id":"025","start_time":"10:20:00","start_stop_name":"VINCIPROVA","finish_time":"10:55:00","finish_stop_name":"OSPEDALE S.LEONARDO - CAPOLINEA","trip_id":"52_818842"},{"route_id":"025","start_time":"10:55:00","start_stop_name":"VINCIPROVA","finish_time":"11:34:00","finish_stop_name":"MONTICELLI - CAPOLINEA","trip_id":"52_818833"},{"route_id":"025","start_time":"11:45:00","start_stop_name":"VINCIPROVA","finish_time":"12:24:00","finish_stop_name":"MONTICELLI - CAPOLINEA","trip_id":"52_818825"},{"route_id":"025","start_time":"12:25:00","start_stop_name":"VINCIPROVA","finish_time":"13:01:00","finish_stop_name":"OSPEDALE S.LEONARDO - CAPOLINEA","trip_id":"52_818843"},{"route_id":"025","start_time":"13:15:00","start_stop_name":"VINCIPROVA","finish_time":"13:55:00","finish_stop_name":"MONTICELLI - CAPOLINEA","trip_id":"52_818826"},{"route_id":"025","start_time":"13:55:00","start_stop_name":"VINCIPROVA","finish_time":"14:32:00","finish_stop_name":"MONTICELLI - CAPOLINEA","trip_id":"52_818827"},{"route_id":"025","start_time":"14:45:00","start_stop_name":"VINCIPROVA","finish_time":"15:16:00","finish_stop_name":"OSPEDALE S.LEONARDO - CAPOLINEA","trip_id":"52_818837"},{"route_id":"025","start_time":"15:25:00","start_stop_name":"VINCIPROVA","finish_time":"16:01:00","finish_stop_name":"MONTICELLI - CAPOLINEA","trip_id":"52_818834"},{"route_id":"025","start_time":"16:10:00","start_stop_name":"VINCIPROVA","finish_time":"16:49:00","finish_stop_name":"MONTICELLI - CAPOLINEA","trip_id":"52_818828"},{"route_id":"025","start_time":"16:55:00","start_stop_name":"VINCIPROVA","finish_time":"17:27:00","finish_stop_name":"OSPEDALE S.LEONARDO - CAPOLINEA","trip_id":"52_818838"},{"route_id":"025","start_time":"17:30:00","start_stop_name":"OSPEDALE S.LEONARDO - CAPOLINEA","finish_time":"17:34:00","finish_stop_name":"MONTICELLI - CAPOLINEA","trip_id":"52_816814"},{"route_id":"025","start_time":"17:45:00","start_stop_name":"VINCIPROVA","finish_time":"18:24:00","finish_stop_name":"MONTICELLI - CAPOLINEA","trip_id":"52_818829"},{"route_id":"025","start_time":"18:30:00","start_stop_name":"VINCIPROVA","finish_time":"19:07:00","finish_stop_name":"MONTICELLI - CAPOLINEA","trip_id":"52_818835"},{"route_id":"025","start_time":"19:15:00","start_stop_name":"VINCIPROVA","finish_time":"19:54:00","finish_stop_name":"MONTICELLI - CAPOLINEA","trip_id":"52_818830"},{"route_id":"025","start_time":"20:15:00","start_stop_name":"VINCIPROVA","finish_time":"20:47:00","finish_stop_name":"OSPEDALE S.LEONARDO - CAPOLINEA","trip_id":"52_818839"},{"route_id":"025","start_time":"21:20:00","start_stop_name":"VINCIPROVA","finish_time":"21:54:00","finish_stop_name":"MONTICELLI - CAPOLINEA","trip_id":"52_818836"},{"route_id":"025","start_time":"22:35:00","start_stop_name":"VINCIPROVA","finish_time":"23:04:00","finish_stop_name":"OSPEDALE S.LEONARDO - CAPOLINEA","trip_id":"52_818840"},{"route_id":"025","start_time":"22:55:00","start_stop_name":"VINCIPROVA","finish_time":"23:23:00","finish_stop_name":"OSPEDALE S.LEONARDO - CAPOLINEA","trip_id":"52_818841"},{"route_id":"025","start_time":"07:15:00","start_stop_name":"MONTICELLI - CAPOLINEA","finish_time":"07:54:00","finish_stop_name":"VINCIPROVA","trip_id":"52_818864"},{"route_id":"025","start_time":"07:55:00","start_stop_name":"MONTICELLI - CAPOLINEA","finish_time":"08:35:00","finish_stop_name":"VINCIPROVA","trip_id":"52_818865"},{"route_id":"025","start_time":"08:45:00","start_stop_name":"MONTICELLI - CAPOLINEA","finish_time":"09:25:00","finish_stop_name":"VINCIPROVA","trip_id":"52_818866"},{"route_id":"025","start_time":"09:30:00","start_stop_name":"MONTICELLI - CAPOLINEA","finish_time":"10:11:00","finish_stop_name":"VINCIPROVA","trip_id":"52_818867"},{"route_id":"025","start_time":"10:15:00","start_stop_name":"MONTICELLI - CAPOLINEA","finish_time":"10:54:00","finish_stop_name":"VINCIPROVA","trip_id":"52_818869"},{"route_id":"025","start_time":"11:05:00","start_stop_name":"OSPEDALE S.LEONARDO - CAPOLINEA","finish_time":"11:39:00","finish_stop_name":"VINCIPROVA","trip_id":"52_818872"},{"route_id":"025","start_time":"11:40:00","start_stop_name":"MONTICELLI - CAPOLINEA","finish_time":"11:47:00","finish_stop_name":"OSPEDALE S.LEONARDO - CAPOLINEA","trip_id":"52_816816"},{"route_id":"025","start_time":"11:47:00","start_stop_name":"OSPEDALE S.LEONARDO - CAPOLINEA","finish_time":"12:23:00","finish_stop_name":"VINCIPROVA","trip_id":"52_818874"},{"route_id":"025","start_time":"12:35:00","start_stop_name":"MONTICELLI - CAPOLINEA","finish_time":"12:41:00","finish_stop_name":"OSPEDALE S.LEONARDO - CAPOLINEA","trip_id":"52_816818"},{"route_id":"025","start_time":"12:41:00","start_stop_name":"OSPEDALE S.LEONARDO - CAPOLINEA","finish_time":"13:15:00","finish_stop_name":"VINCIPROVA","trip_id":"52_818875"},{"route_id":"025","start_time":"13:10:00","start_stop_name":"OSPEDALE S.LEONARDO - CAPOLINEA","finish_time":"13:44:00","finish_stop_name":"VINCIPROVA","trip_id":"52_818876"},{"route_id":"025","start_time":"14:00:00","start_stop_name":"MONTICELLI - CAPOLINEA","finish_time":"14:06:00","finish_stop_name":"OSPEDALE S.LEONARDO - CAPOLINEA","trip_id":"52_816820"},{"route_id":"025","start_time":"14:06:00","start_stop_name":"OSPEDALE S.LEONARDO - CAPOLINEA","finish_time":"14:39:00","finish_stop_name":"VINCIPROVA","trip_id":"52_818877"},{"route_id":"025","start_time":"14:40:00","start_stop_name":"MONTICELLI - CAPOLINEA","finish_time":"15:17:00","finish_stop_name":"VINCIPROVA","trip_id":"52_818870"},{"route_id":"025","start_time":"15:25:00","start_stop_name":"OSPEDALE S.LEONARDO - CAPOLINEA","finish_time":"15:59:00","finish_stop_name":"VINCIPROVA","trip_id":"52_818878"},{"route_id":"025","start_time":"16:15:00","start_stop_name":"MONTICELLI - CAPOLINEA","finish_time":"16:21:00","finish_stop_name":"OSPEDALE S.LEONARDO - CAPOLINEA","trip_id":"52_816822"},{"route_id":"025","start_time":"16:21:00","start_stop_name":"OSPEDALE S.LEONARDO - CAPOLINEA","finish_time":"16:55:00","finish_stop_name":"VINCIPROVA","trip_id":"52_818879"},{"route_id":"025","start_time":"17:00:00","start_stop_name":"MONTICELLI - CAPOLINEA","finish_time":"17:38:00","finish_stop_name":"VINCIPROVA","trip_id":"52_818871"},{"route_id":"025","start_time":"17:40:00","start_stop_name":"MONTICELLI - CAPOLINEA","finish_time":"18:20:00","finish_stop_name":"VINCIPROVA","trip_id":"52_818868"},{"route_id":"025","start_time":"18:35:00","start_stop_name":"MONTICELLI - CAPOLINEA","finish_time":"18:41:00","finish_stop_name":"OSPEDALE S.LEONARDO - CAPOLINEA","trip_id":"52_816824"},{"route_id":"025","start_time":"18:41:00","start_stop_name":"OSPEDALE S.LEONARDO - CAPOLINEA","finish_time":"19:14:00","finish_stop_name":"VINCIPROVA","trip_id":"52_818873"},{"route_id":"025","start_time":"19:15:00","start_stop_name":"MONTICELLI - CAPOLINEA","finish_time":"19:21:00","finish_stop_name":"OSPEDALE S.LEONARDO - CAPOLINEA","trip_id":"52_816826"},{"route_id":"025","start_time":"19:21:00","start_stop_name":"OSPEDALE S.LEONARDO - CAPOLINEA","finish_time":"19:55:00","finish_stop_name":"VINCIPROVA","trip_id":"52_818880"},{"route_id":"025","start_time":"20:50:00","start_stop_name":"OSPEDALE S.LEONARDO - CAPOLINEA","finish_time":"21:20:00","finish_stop_name":"VINCIPROVA","trip_id":"52_818881"},{"route_id":"025","start_time":"22:00:00","start_stop_name":"MONTICELLI - CAPOLINEA","finish_time":"22:05:00","finish_stop_name":"OSPEDALE S.LEONARDO - CAPOLINEA","trip_id":"52_816828"},{"route_id":"025","start_time":"22:05:00","start_stop_name":"OSPEDALE S.LEONARDO - CAPOLINEA","finish_time":"22:35:00","finish_stop_name":"VINCIPROVA","trip_id":"52_818882"},{"route_id":"033","start_time":"07:10:00","start_stop_name":"ALBANELLA (CAPOLINEA)","finish_time":"09:20:00","finish_stop_name":"SALERNO STAZIONE","trip_id":"52_819368"},{"route_id":"033","start_time":"12:30:00","start_stop_name":"LIGEA  CAPOLINEA","finish_time":"14:35:00","finish_stop_name":"ALBANELLA (CAPOLINEA)","trip_id":"52_815735"},{"route_id":"034","start_time":"06:20:00","start_stop_name":"GALDO(CAP.)","finish_time":"07:10:00","finish_stop_name":"S. MARIA DI CASTELLABATE CAPOLINEA","trip_id":"52_817517"},{"route_id":"034","start_time":"07:30:00","start_stop_name":"S. MARIA DI CASTELLABATE CAPOLINEA","finish_time":"09:48:00","finish_stop_name":"VINCIPROVA","trip_id":"52_819388"},{"route_id":"034","start_time":"09:20:00","start_stop_name":"S. MARCO DI CASTELLABATE","finish_time":"11:48:00","finish_stop_name":"VINCIPROVA","trip_id":"52_819379"},{"route_id":"034","start_time":"09:50:00","start_stop_name":"ACCIAROLI PORTO","finish_time":"12:43:00","finish_stop_name":"VINCIPROVA","trip_id":"52_819371"},{"route_id":"034","start_time":"11:30:00","start_stop_name":"S. MARIA DI CASTELLABATE CAPOLINEA","finish_time":"13:18:00","finish_stop_name":"VINCIPROVA","trip_id":"52_819387"},{"route_id":"034","start_time":"12:50:00","start_stop_name":"ACCIAROLI PORTO","finish_time":"13:30:00","finish_stop_name":"S. MARCO DI CASTELLABATE","trip_id":"52_816568"},{"route_id":"034","start_time":"13:30:00","start_stop_name":"S. MARCO DI CASTELLABATE","finish_time":"15:33:00","finish_stop_name":"VINCIPROVA","trip_id":"52_819380"},{"route_id":"034","start_time":"14:20:00","start_stop_name":"S. MARCO DI CASTELLABATE","finish_time":"16:18:00","finish_stop_name":"VINCIPROVA","trip_id":"52_819381"},{"route_id":"034","start_time":"15:05:00","start_stop_name":"GALDO(CAP.)","finish_time":"16:00:00","finish_stop_name":"S. MARIA DI CASTELLABATE CAPOLINEA","trip_id":"52_816565"},{"route_id":"034","start_time":"15:20:00","start_stop_name":"S. MARCO DI CASTELLABATE","finish_time":"17:23:00","finish_stop_name":"VINCIPROVA","trip_id":"52_819385"},{"route_id":"034","start_time":"16:20:00","start_stop_name":"ACCIAROLI PORTO","finish_time":"17:20:00","finish_stop_name":"AGROPOLI TENDOSTRUTTURA (VERSO SALERNO)","trip_id":"52_815596"},{"route_id":"034","start_time":"17:35:00","start_stop_name":"GALDO(CAP.)","finish_time":"18:00:00","finish_stop_name":"ACCIAROLI PORTO","trip_id":"52_815727"},{"route_id":"034","start_time":"18:50:00","start_stop_name":"ACCIAROLI PORTO","finish_time":"21:28:00","finish_stop_name":"VINCIPROVA","trip_id":"52_819376"},{"route_id":"034","start_time":"05:30:00","start_stop_name":"S. MARIA DI CASTELLABATE CAPOLINEA","finish_time":"06:20:00","finish_stop_name":"GALDO(CAP.)","trip_id":"52_816558"},{"route_id":"034","start_time":"06:30:00","start_stop_name":"CONCORDIA","finish_time":"08:50:00","finish_stop_name":"ACCIAROLI PORTO","trip_id":"52_818248"},{"route_id":"034","start_time":"07:30:00","start_stop_name":"CONCORDIA","finish_time":"09:30:00","finish_stop_name":"S. MARCO DI CASTELLABATE","trip_id":"52_816559"},{"route_id":"034","start_time":"09:30:00","start_stop_name":"CONCORDIA","finish_time":"12:00:00","finish_stop_name":"ACCIAROLI PORTO","trip_id":"52_816560"},{"route_id":"034","start_time":"10:30:00","start_stop_name":"CONCORDIA","finish_time":"12:30:00","finish_stop_name":"S. MARCO DI CASTELLABATE","trip_id":"52_816561"},{"route_id":"034","start_time":"11:30:00","start_stop_name":"CONCORDIA","finish_time":"13:25:00","finish_stop_name":"S. MARCO DI CASTELLABATE","trip_id":"52_816562"},{"route_id":"034","start_time":"12:30:00","start_stop_name":"CONCORDIA","finish_time":"14:10:00","finish_stop_name":"S. MARCO DI CASTELLABATE","trip_id":"52_816563"},{"route_id":"034","start_time":"14:15:00","start_stop_name":"S. MARCO DI CASTELLABATE","finish_time":"15:00:00","finish_stop_name":"GALDO(CAP.)","trip_id":"52_818255"},{"route_id":"034","start_time":"14:30:00","start_stop_name":"CONCORDIA","finish_time":"17:25:00","finish_stop_name":"GALDO(CAP.)","trip_id":"52_815726"},{"route_id":"034","start_time":"15:30:00","start_stop_name":"S. MARCO DI CASTELLABATE","finish_time":"16:00:00","finish_stop_name":"ACCIAROLI PORTO","trip_id":"52_817520"},{"route_id":"034","start_time":"16:35:00","start_stop_name":"CONCORDIA","finish_time":"18:20:00","finish_stop_name":"S. MARCO DI CASTELLABATE","trip_id":"52_816567"},{"route_id":"034","start_time":"17:30:00","start_stop_name":"AGROPOLI TENDOSTRUTTURA (VERSO S. MARIA)","finish_time":"17:50:00","finish_stop_name":"S. MARIA DI CASTELLABATE CAPOLINEA","trip_id":"52_815597"},{"route_id":"034","start_time":"17:45:00","start_stop_name":"CONCORDIA","finish_time":"19:25:00","finish_stop_name":"S. MARCO DI CASTELLABATE","trip_id":"52_817190"},{"route_id":"041","start_time":"07:15:00","start_stop_name":"VINCIPROVA","finish_time":"07:35:00","finish_stop_name":"OLMI - CAPOLINEA","trip_id":"52_819077"},{"route_id":"041","start_time":"09:15:00","start_stop_name":"VINCIPROVA","finish_time":"09:35:00","finish_stop_name":"SALA ABBAGNANO PIOPPI","trip_id":"52_819079"},{"route_id":"041","start_time":"10:05:00","start_stop_name":"VINCIPROVA","finish_time":"10:25:00","finish_stop_name":"SALA ABBAGNANO PIOPPI","trip_id":"52_819080"},{"route_id":"041","start_time":"13:05:00","start_stop_name":"VINCIPROVA","finish_time":"13:26:00","finish_stop_name":"OLMI - CAPOLINEA","trip_id":"52_819078"},{"route_id":"041","start_time":"07:35:00","start_stop_name":"OLMI - CAPOLINEA","finish_time":"07:45:00","finish_stop_name":"VINCIPROVA","trip_id":"52_819081"},{"route_id":"041","start_time":"09:35:00","start_stop_name":"SALA ABBAGNANO PIOPPI","finish_time":"09:44:00","finish_stop_name":"VINCIPROVA","trip_id":"52_819083"},{"route_id":"041","start_time":"10:25:00","start_stop_name":"SALA ABBAGNANO PIOPPI","finish_time":"10:34:00","finish_stop_name":"VINCIPROVA","trip_id":"52_819084"},{"route_id":"041","start_time":"13:30:00","start_stop_name":"OLMI - CAPOLINEA","finish_time":"13:40:00","finish_stop_name":"VINCIPROVA","trip_id":"52_819082"},{"route_id":"009","start_time":"05:25:00","start_stop_name":"NOCERA SUP. CAMERELLE","finish_time":"06:10:00","finish_stop_name":"VINCIPROVA","trip_id":"52_819539"},{"route_id":"009","start_time":"05:35:00","start_stop_name":"SIANO","finish_time":"06:45:00","finish_stop_name":"VINCIPROVA","trip_id":"52_819518"},{"route_id":"009","start_time":"06:20:00","start_stop_name":"SIANO","finish_time":"07:30:00","finish_stop_name":"VINCIPROVA","trip_id":"52_819519"},{"route_id":"009","start_time":"07:00:00","start_stop_name":"SIANO","finish_time":"08:10:00","finish_stop_name":"VINCIPROVA","trip_id":"52_819520"},{"route_id":"009","start_time":"07:30:00","start_stop_name":"SIANO","finish_time":"08:45:00","finish_stop_name":"VINCIPROVA","trip_id":"52_819521"},{"route_id":"009","start_time":"08:05:00","start_stop_name":"SIANO","finish_time":"09:20:00","finish_stop_name":"VINCIPROVA","trip_id":"52_819522"},{"route_id":"009","start_time":"09:00:00","start_stop_name":"SIANO","finish_time":"10:15:00","finish_stop_name":"VINCIPROVA","trip_id":"52_819523"},{"route_id":"009","start_time":"09:45:00","start_stop_name":"SIANO","finish_time":"11:00:00","finish_stop_name":"VINCIPROVA","trip_id":"52_819524"},{"route_id":"009","start_time":"10:30:00","start_stop_name":"SIANO","finish_time":"11:45:00","finish_stop_name":"VINCIPROVA","trip_id":"52_819525"},{"route_id":"009","start_time":"11:15:00","start_stop_name":"SIANO","finish_time":"12:30:00","finish_stop_name":"VINCIPROVA","trip_id":"52_819526"},{"route_id":"009","start_time":"12:00:00","start_stop_name":"SIANO","finish_time":"13:15:00","finish_stop_name":"VINCIPROVA","trip_id":"52_819527"},{"route_id":"009","start_time":"12:45:00","start_stop_name":"SIANO","finish_time":"14:00:00","finish_stop_name":"VINCIPROVA","trip_id":"52_819528"},{"route_id":"009","start_time":"13:30:00","start_stop_name":"SIANO","finish_time":"14:45:00","finish_stop_name":"VINCIPROVA","trip_id":"52_819529"},{"route_id":"009","start_time":"14:15:00","start_stop_name":"SIANO","finish_time":"15:30:00","finish_stop_name":"VINCIPROVA","trip_id":"52_819530"},{"route_id":"009","start_time":"15:00:00","start_stop_name":"SIANO","finish_time":"16:15:00","finish_stop_name":"VINCIPROVA","trip_id":"52_819531"},{"route_id":"009","start_time":"15:45:00","start_stop_name":"SIANO","finish_time":"17:00:00","finish_stop_name":"VINCIPROVA","trip_id":"52_819532"},{"route_id":"009","start_time":"16:25:00","start_stop_name":"SIANO","finish_time":"17:40:00","finish_stop_name":"VINCIPROVA","trip_id":"52_819533"},{"route_id":"009","start_time":"17:15:00","start_stop_name":"SIANO","finish_time":"18:30:00","finish_stop_name":"VINCIPROVA","trip_id":"52_819534"},{"route_id":"009","start_time":"18:00:00","start_stop_name":"SIANO","finish_time":"19:15:00","finish_stop_name":"VINCIPROVA","trip_id":"52_819535"},{"route_id":"009","start_time":"19:20:00","start_stop_name":"SIANO","finish_time":"20:35:00","finish_stop_name":"VINCIPROVA","trip_id":"52_819536"},{"route_id":"009","start_time":"20:15:00","start_stop_name":"SIANO","finish_time":"21:30:00","finish_stop_name":"VINCIPROVA","trip_id":"52_819537"},{"route_id":"009","start_time":"21:00:00","start_stop_name":"SIANO","finish_time":"22:15:00","finish_stop_name":"VINCIPROVA","trip_id":"52_819538"},{"route_id":"009","start_time":"22:15:00","start_stop_name":"SIANO","finish_time":"22:40:00","finish_stop_name":"CAMERELLE","trip_id":"52_819540"},{"route_id":"009","start_time":"23:00:00","start_stop_name":"SIANO","finish_time":"23:25:00","finish_stop_name":"CAMERELLE","trip_id":"52_819541"},{"route_id":"009","start_time":"05:10:00","start_stop_name":"CAMERELLE","finish_time":"05:35:00","finish_stop_name":"SIANO","trip_id":"52_819563"},{"route_id":"009","start_time":"05:55:00","start_stop_name":"CAMERELLE","finish_time":"06:20:00","finish_stop_name":"SIANO","trip_id":"52_819564"},{"route_id":"009","start_time":"06:15:00","start_stop_name":"VINCIPROVA","finish_time":"07:25:00","finish_stop_name":"SIANO","trip_id":"52_819542"},{"route_id":"009","start_time":"06:30:00","start_stop_name":"CAMERELLE","finish_time":"06:55:00","finish_stop_name":"SIANO","trip_id":"52_819565"},{"route_id":"009","start_time":"06:50:00","start_stop_name":"VINCIPROVA","finish_time":"08:00:00","finish_stop_name":"SIANO","trip_id":"52_819543"},{"route_id":"009","start_time":"07:40:00","start_stop_name":"VINCIPROVA","finish_time":"08:50:00","finish_stop_name":"SIANO","trip_id":"52_819544"},{"route_id":"009","start_time":"08:20:00","start_stop_name":"VINCIPROVA","finish_time":"09:35:00","finish_stop_name":"SIANO","trip_id":"52_819545"},{"route_id":"009","start_time":"09:00:00","start_stop_name":"VINCIPROVA","finish_time":"10:15:00","finish_stop_name":"SIANO","trip_id":"52_819546"},{"route_id":"009","start_time":"09:45:00","start_stop_name":"VINCIPROVA","finish_time":"11:00:00","finish_stop_name":"SIANO","trip_id":"52_819547"},{"route_id":"009","start_time":"10:30:00","start_stop_name":"VINCIPROVA","finish_time":"11:45:00","finish_stop_name":"SIANO","trip_id":"52_819548"},{"route_id":"009","start_time":"11:15:00","start_stop_name":"VINCIPROVA","finish_time":"12:30:00","finish_stop_name":"SIANO","trip_id":"52_819549"},{"route_id":"009","start_time":"12:00:00","start_stop_name":"VINCIPROVA","finish_time":"13:15:00","finish_stop_name":"SIANO","trip_id":"52_819550"},{"route_id":"009","start_time":"12:45:00","start_stop_name":"VINCIPROVA","finish_time":"14:00:00","finish_stop_name":"SIANO","trip_id":"52_819551"},{"route_id":"009","start_time":"13:30:00","start_stop_name":"VINCIPROVA","finish_time":"14:45:00","finish_stop_name":"SIANO","trip_id":"52_819552"},{"route_id":"009","start_time":"14:15:00","start_stop_name":"VINCIPROVA","finish_time":"15:30:00","finish_stop_name":"SIANO","trip_id":"52_819553"},{"route_id":"009","start_time":"15:00:00","start_stop_name":"VINCIPROVA","finish_time":"16:15:00","finish_stop_name":"SIANO","trip_id":"52_819554"},{"route_id":"009","start_time":"15:45:00","start_stop_name":"VINCIPROVA","finish_time":"17:00:00","finish_stop_name":"SIANO","trip_id":"52_819555"},{"route_id":"009","start_time":"16:30:00","start_stop_name":"VINCIPROVA","finish_time":"17:45:00","finish_stop_name":"SIANO","trip_id":"52_819556"},{"route_id":"009","start_time":"17:15:00","start_stop_name":"VINCIPROVA","finish_time":"18:30:00","finish_stop_name":"SIANO","trip_id":"52_819557"},{"route_id":"009","start_time":"17:50:00","start_stop_name":"VINCIPROVA","finish_time":"19:05:00","finish_stop_name":"SIANO","trip_id":"52_819558"},{"route_id":"009","start_time":"18:45:00","start_stop_name":"VINCIPROVA","finish_time":"20:00:00","finish_stop_name":"SIANO","trip_id":"52_819559"},{"route_id":"009","start_time":"19:30:00","start_stop_name":"VINCIPROVA","finish_time":"20:45:00","finish_stop_name":"SIANO","trip_id":"52_819560"},{"route_id":"009","start_time":"20:45:00","start_stop_name":"VINCIPROVA","finish_time":"22:00:00","finish_stop_name":"SIANO","trip_id":"52_819561"},{"route_id":"009","start_time":"21:45:00","start_stop_name":"VINCIPROVA","finish_time":"23:00:00","finish_stop_name":"SIANO","trip_id":"52_819562"},{"route_id":"009","start_time":"22:30:00","start_stop_name":"VINCIPROVA","finish_time":"23:10:00","finish_stop_name":"CAMERELLE","trip_id":"52_819566"},{"route_id":"010","start_time":"05:10:00","start_stop_name":"VINCIPROVA","finish_time":"05:47:00","finish_stop_name":"M.S.SEVERINO (CAPOLINEA)","trip_id":"52_819166"},{"route_id":"010","start_time":"06:00:00","start_stop_name":"VINCIPROVA","finish_time":"06:37:00","finish_stop_name":"M.S.SEVERINO (CAPOLINEA)","trip_id":"52_819168"},{"route_id":"010","start_time":"06:35:00","start_stop_name":"VINCIPROVA","finish_time":"07:15:00","finish_stop_name":"M.S.SEVERINO (CAPOLINEA)","trip_id":"52_819169"},{"route_id":"010","start_time":"07:05:00","start_stop_name":"VINCIPROVA","finish_time":"07:48:00","finish_stop_name":"M.S.SEVERINO (CAPOLINEA)","trip_id":"52_819171"},{"route_id":"010","start_time":"07:45:00","start_stop_name":"VINCIPROVA","finish_time":"08:32:00","finish_stop_name":"M.S.SEVERINO (CAPOLINEA)","trip_id":"52_819172"},{"route_id":"010","start_time":"08:15:00","start_stop_name":"VINCIPROVA","finish_time":"09:03:00","finish_stop_name":"M.S.SEVERINO (CAPOLINEA)","trip_id":"52_819174"},{"route_id":"010","start_time":"08:45:00","start_stop_name":"VINCIPROVA","finish_time":"09:33:00","finish_stop_name":"M.S.SEVERINO (CAPOLINEA)","trip_id":"52_819175"},{"route_id":"010","start_time":"09:20:00","start_stop_name":"VINCIPROVA","finish_time":"10:08:00","finish_stop_name":"M.S.SEVERINO (CAPOLINEA)","trip_id":"52_819211"},{"route_id":"010","start_time":"09:45:00","start_stop_name":"VINCIPROVA","finish_time":"10:33:00","finish_stop_name":"M.S.SEVERINO (CAPOLINEA)","trip_id":"52_819212"},{"route_id":"010","start_time":"10:15:00","start_stop_name":"VINCIPROVA","finish_time":"11:03:00","finish_stop_name":"M.S.SEVERINO (CAPOLINEA)","trip_id":"52_819180"},{"route_id":"010","start_time":"10:45:00","start_stop_name":"VINCIPROVA","finish_time":"11:33:00","finish_stop_name":"M.S.SEVERINO (CAPOLINEA)","trip_id":"52_819181"},{"route_id":"010","start_time":"11:15:00","start_stop_name":"VINCIPROVA","finish_time":"12:03:00","finish_stop_name":"M.S.SEVERINO (CAPOLINEA)","trip_id":"52_819183"},{"route_id":"010","start_time":"11:45:00","start_stop_name":"VINCIPROVA","finish_time":"12:33:00","finish_stop_name":"M.S.SEVERINO (CAPOLINEA)","trip_id":"52_819184"},{"route_id":"010","start_time":"12:15:00","start_stop_name":"VINCIPROVA","finish_time":"13:03:00","finish_stop_name":"M.S.SEVERINO (CAPOLINEA)","trip_id":"52_819213"},{"route_id":"010","start_time":"12:45:00","start_stop_name":"VINCIPROVA","finish_time":"13:33:00","finish_stop_name":"M.S.SEVERINO (CAPOLINEA)","trip_id":"52_819214"},{"route_id":"010","start_time":"13:10:00","start_stop_name":"VINCIPROVA","finish_time":"13:59:00","finish_stop_name":"M.S.SEVERINO (CAPOLINEA)","trip_id":"52_819187"},{"route_id":"010","start_time":"13:40:00","start_stop_name":"VINCIPROVA","finish_time":"14:28:00","finish_stop_name":"M.S.SEVERINO (CAPOLINEA)","trip_id":"52_819188"},{"route_id":"010","start_time":"14:15:00","start_stop_name":"VINCIPROVA","finish_time":"15:02:00","finish_stop_name":"M.S.SEVERINO (CAPOLINEA)","trip_id":"52_819190"},{"route_id":"010","start_time":"14:40:00","start_stop_name":"VINCIPROVA","finish_time":"15:28:00","finish_stop_name":"M.S.SEVERINO (CAPOLINEA)","trip_id":"52_819191"},{"route_id":"010","start_time":"15:15:00","start_stop_name":"VINCIPROVA","finish_time":"16:02:00","finish_stop_name":"M.S.SEVERINO (CAPOLINEA)","trip_id":"52_819215"},{"route_id":"010","start_time":"15:45:00","start_stop_name":"VINCIPROVA","finish_time":"16:32:00","finish_stop_name":"M.S.SEVERINO (CAPOLINEA)","trip_id":"52_819193"},{"route_id":"010","start_time":"16:15:00","start_stop_name":"VINCIPROVA","finish_time":"17:03:00","finish_stop_name":"M.S.SEVERINO (CAPOLINEA)","trip_id":"52_819195"},{"route_id":"010","start_time":"16:45:00","start_stop_name":"VINCIPROVA","finish_time":"17:35:00","finish_stop_name":"M.S.SEVERINO (CAPOLINEA)","trip_id":"52_819216"},{"route_id":"010","start_time":"17:15:00","start_stop_name":"VINCIPROVA","finish_time":"18:05:00","finish_stop_name":"M.S.SEVERINO (CAPOLINEA)","trip_id":"52_819197"},{"route_id":"010","start_time":"17:45:00","start_stop_name":"VINCIPROVA","finish_time":"18:35:00","finish_stop_name":"M.S.SEVERINO (CAPOLINEA)","trip_id":"52_819198"},{"route_id":"010","start_time":"18:15:00","start_stop_name":"VINCIPROVA","finish_time":"19:05:00","finish_stop_name":"M.S.SEVERINO (CAPOLINEA)","trip_id":"52_819217"},{"route_id":"010","start_time":"18:45:00","start_stop_name":"VINCIPROVA","finish_time":"19:34:00","finish_stop_name":"M.S.SEVERINO (CAPOLINEA)","trip_id":"52_819218"},{"route_id":"010","start_time":"19:15:00","start_stop_name":"VINCIPROVA","finish_time":"20:04:00","finish_stop_name":"M.S.SEVERINO (CAPOLINEA)","trip_id":"52_819219"},{"route_id":"010","start_time":"19:45:00","start_stop_name":"VINCIPROVA","finish_time":"20:34:00","finish_stop_name":"M.S.SEVERINO (CAPOLINEA)","trip_id":"52_819201"},{"route_id":"010","start_time":"20:15:00","start_stop_name":"VINCIPROVA","finish_time":"21:02:00","finish_stop_name":"M.S.SEVERINO (CAPOLINEA)","trip_id":"52_819203"},{"route_id":"010","start_time":"20:45:00","start_stop_name":"VINCIPROVA","finish_time":"21:31:00","finish_stop_name":"M.S.SEVERINO (CAPOLINEA)","trip_id":"52_819204"},{"route_id":"010","start_time":"21:15:00","start_stop_name":"VINCIPROVA","finish_time":"21:55:00","finish_stop_name":"M.S.SEVERINO (CAPOLINEA)","trip_id":"52_819206"},{"route_id":"010","start_time":"21:45:00","start_stop_name":"VINCIPROVA","finish_time":"22:25:00","finish_stop_name":"M.S.SEVERINO (CAPOLINEA)","trip_id":"52_819207"},{"route_id":"010","start_time":"22:15:00","start_stop_name":"VINCIPROVA","finish_time":"22:55:00","finish_stop_name":"M.S.SEVERINO (CAPOLINEA)","trip_id":"52_819209"},{"route_id":"010","start_time":"05:15:00","start_stop_name":"M.S.SEVERINO (CAPOLINEA)","finish_time":"05:55:00","finish_stop_name":"VINCIPROVA","trip_id":"52_819220"},{"route_id":"010","start_time":"05:50:00","start_stop_name":"M.S.SEVERINO (CAPOLINEA)","finish_time":"06:30:00","finish_stop_name":"VINCIPROVA","trip_id":"52_819221"},{"route_id":"010","start_time":"06:40:00","start_stop_name":"M.S.SEVERINO (CAPOLINEA)","finish_time":"07:29:00","finish_stop_name":"VINCIPROVA","trip_id":"52_819223"},{"route_id":"010","start_time":"07:20:00","start_stop_name":"M.S.SEVERINO (CAPOLINEA)","finish_time":"08:13:00","finish_stop_name":"VINCIPROVA","trip_id":"52_819225"},{"route_id":"010","start_time":"08:00:00","start_stop_name":"M.S.SEVERINO (CAPOLINEA)","finish_time":"08:53:00","finish_stop_name":"VINCIPROVA","trip_id":"52_819227"},{"route_id":"010","start_time":"08:45:00","start_stop_name":"M.S.SEVERINO (CAPOLINEA)","finish_time":"09:38:00","finish_stop_name":"VINCIPROVA","trip_id":"52_819228"},{"route_id":"010","start_time":"09:15:00","start_stop_name":"M.S.SEVERINO (CAPOLINEA)","finish_time":"10:08:00","finish_stop_name":"VINCIPROVA","trip_id":"52_819230"},{"route_id":"010","start_time":"09:45:00","start_stop_name":"M.S.SEVERINO (CAPOLINEA)","finish_time":"10:36:00","finish_stop_name":"VINCIPROVA","trip_id":"52_819231"},{"route_id":"010","start_time":"10:15:00","start_stop_name":"M.S.SEVERINO (CAPOLINEA)","finish_time":"11:05:00","finish_stop_name":"VINCIPROVA","trip_id":"52_819233"},{"route_id":"010","start_time":"10:45:00","start_stop_name":"M.S.SEVERINO (CAPOLINEA)","finish_time":"11:35:00","finish_stop_name":"VINCIPROVA","trip_id":"52_819234"},{"route_id":"010","start_time":"11:15:00","start_stop_name":"M.S.SEVERINO (CAPOLINEA)","finish_time":"12:05:00","finish_stop_name":"VINCIPROVA","trip_id":"52_819236"},{"route_id":"010","start_time":"11:45:00","start_stop_name":"M.S.SEVERINO (CAPOLINEA)","finish_time":"12:33:00","finish_stop_name":"VINCIPROVA","trip_id":"52_819237"},{"route_id":"010","start_time":"12:15:00","start_stop_name":"M.S.SEVERINO (CAPOLINEA)","finish_time":"13:03:00","finish_stop_name":"VINCIPROVA","trip_id":"52_819239"},{"route_id":"010","start_time":"12:45:00","start_stop_name":"M.S.SEVERINO (CAPOLINEA)","finish_time":"13:33:00","finish_stop_name":"VINCIPROVA","trip_id":"52_819240"},{"route_id":"010","start_time":"13:15:00","start_stop_name":"M.S.SEVERINO (CAPOLINEA)","finish_time":"14:03:00","finish_stop_name":"VINCIPROVA","trip_id":"52_819242"},{"route_id":"010","start_time":"13:45:00","start_stop_name":"M.S.SEVERINO (CAPOLINEA)","finish_time":"14:33:00","finish_stop_name":"VINCIPROVA","trip_id":"52_819243"},{"route_id":"010","start_time":"14:15:00","start_stop_name":"M.S.SEVERINO (CAPOLINEA)","finish_time":"15:03:00","finish_stop_name":"VINCIPROVA","trip_id":"52_819245"},{"route_id":"010","start_time":"14:45:00","start_stop_name":"M.S.SEVERINO (CAPOLINEA)","finish_time":"15:33:00","finish_stop_name":"VINCIPROVA","trip_id":"52_819246"},{"route_id":"010","start_time":"15:15:00","start_stop_name":"M.S.SEVERINO (CAPOLINEA)","finish_time":"16:03:00","finish_stop_name":"VINCIPROVA","trip_id":"52_819248"},{"route_id":"010","start_time":"15:45:00","start_stop_name":"M.S.SEVERINO (CAPOLINEA)","finish_time":"16:35:00","finish_stop_name":"VINCIPROVA","trip_id":"52_819249"},{"route_id":"010","start_time":"16:15:00","start_stop_name":"M.S.SEVERINO (CAPOLINEA)","finish_time":"17:05:00","finish_stop_name":"VINCIPROVA","trip_id":"52_819251"},{"route_id":"010","start_time":"16:45:00","start_stop_name":"M.S.SEVERINO (CAPOLINEA)","finish_time":"17:38:00","finish_stop_name":"VINCIPROVA","trip_id":"52_819252"},{"route_id":"010","start_time":"17:15:00","start_stop_name":"M.S.SEVERINO (CAPOLINEA)","finish_time":"18:08:00","finish_stop_name":"VINCIPROVA","trip_id":"52_819254"},{"route_id":"010","start_time":"17:45:00","start_stop_name":"M.S.SEVERINO (CAPOLINEA)","finish_time":"18:38:00","finish_stop_name":"VINCIPROVA","trip_id":"52_819255"},{"route_id":"010","start_time":"18:15:00","start_stop_name":"M.S.SEVERINO (CAPOLINEA)","finish_time":"19:08:00","finish_stop_name":"VINCIPROVA","trip_id":"52_819257"},{"route_id":"010","start_time":"18:45:00","start_stop_name":"M.S.SEVERINO (CAPOLINEA)","finish_time":"19:38:00","finish_stop_name":"VINCIPROVA","trip_id":"52_819258"},{"route_id":"010","start_time":"19:15:00","start_stop_name":"M.S.SEVERINO (CAPOLINEA)","finish_time":"20:08:00","finish_stop_name":"VINCIPROVA","trip_id":"52_819260"},{"route_id":"010","start_time":"19:45:00","start_stop_name":"M.S.SEVERINO (CAPOLINEA)","finish_time":"20:35:00","finish_stop_name":"VINCIPROVA","trip_id":"52_819261"},{"route_id":"010","start_time":"20:15:00","start_stop_name":"M.S.SEVERINO (CAPOLINEA)","finish_time":"21:00:00","finish_stop_name":"VINCIPROVA","trip_id":"52_819263"},{"route_id":"010","start_time":"20:45:00","start_stop_name":"M.S.SEVERINO (CAPOLINEA)","finish_time":"21:24:00","finish_stop_name":"VINCIPROVA","trip_id":"52_819264"},{"route_id":"010","start_time":"21:15:00","start_stop_name":"M.S.SEVERINO (CAPOLINEA)","finish_time":"21:54:00","finish_stop_name":"VINCIPROVA","trip_id":"52_819266"},{"route_id":"010","start_time":"21:45:00","start_stop_name":"M.S.SEVERINO (CAPOLINEA)","finish_time":"22:23:00","finish_stop_name":"VINCIPROVA","trip_id":"52_819267"},{"route_id":"010","start_time":"22:15:00","start_stop_name":"M.S.SEVERINO (CAPOLINEA)","finish_time":"22:53:00","finish_stop_name":"VINCIPROVA","trip_id":"52_819269"},{"route_id":"010","start_time":"22:45:00","start_stop_name":"M.S.SEVERINO (CAPOLINEA)","finish_time":"23:23:00","finish_stop_name":"VINCIPROVA","trip_id":"52_819270"},{"route_id":"010","start_time":"23:15:00","start_stop_name":"M.S.SEVERINO (CAPOLINEA)","finish_time":"23:53:00","finish_stop_name":"VINCIPROVA","trip_id":"52_819272"},{"route_id":"012","start_time":"05:50:00","start_stop_name":"SETTEMBRINI CAPOLINEA","finish_time":"06:21:00","finish_stop_name":"S.FRANCESCO","trip_id":"52_818670"},{"route_id":"012","start_time":"07:00:00","start_stop_name":"SETTEMBRINI CAPOLINEA","finish_time":"07:36:00","finish_stop_name":"S.FRANCESCO","trip_id":"52_818671"},{"route_id":"012","start_time":"07:40:00","start_stop_name":"SETTEMBRINI CAPOLINEA","finish_time":"08:19:00","finish_stop_name":"S.FRANCESCO","trip_id":"52_818672"},{"route_id":"012","start_time":"08:20:00","start_stop_name":"SETTEMBRINI CAPOLINEA","finish_time":"09:02:00","finish_stop_name":"S.FRANCESCO","trip_id":"52_818673"},{"route_id":"012","start_time":"09:00:00","start_stop_name":"SETTEMBRINI CAPOLINEA","finish_time":"09:43:00","finish_stop_name":"S.FRANCESCO","trip_id":"52_818674"},{"route_id":"012","start_time":"09:40:00","start_stop_name":"SETTEMBRINI CAPOLINEA","finish_time":"10:22:00","finish_stop_name":"S.FRANCESCO","trip_id":"52_818675"},{"route_id":"012","start_time":"10:20:00","start_stop_name":"SETTEMBRINI CAPOLINEA","finish_time":"11:02:00","finish_stop_name":"S.FRANCESCO","trip_id":"52_818676"},{"route_id":"012","start_time":"11:00:00","start_stop_name":"SETTEMBRINI CAPOLINEA","finish_time":"11:42:00","finish_stop_name":"S.FRANCESCO","trip_id":"52_818677"},{"route_id":"012","start_time":"11:40:00","start_stop_name":"SETTEMBRINI CAPOLINEA","finish_time":"12:22:00","finish_stop_name":"S.FRANCESCO","trip_id":"52_818678"},{"route_id":"012","start_time":"12:20:00","start_stop_name":"SETTEMBRINI CAPOLINEA","finish_time":"13:02:00","finish_stop_name":"S.FRANCESCO","trip_id":"52_818679"},{"route_id":"012","start_time":"13:00:00","start_stop_name":"SETTEMBRINI CAPOLINEA","finish_time":"13:41:00","finish_stop_name":"S.FRANCESCO","trip_id":"52_818680"},{"route_id":"012","start_time":"13:40:00","start_stop_name":"SETTEMBRINI CAPOLINEA","finish_time":"14:20:00","finish_stop_name":"S.FRANCESCO","trip_id":"52_818681"},{"route_id":"012","start_time":"14:20:00","start_stop_name":"SETTEMBRINI CAPOLINEA","finish_time":"15:00:00","finish_stop_name":"S.FRANCESCO","trip_id":"52_818682"},{"route_id":"012","start_time":"15:00:00","start_stop_name":"SETTEMBRINI CAPOLINEA","finish_time":"15:40:00","finish_stop_name":"S.FRANCESCO","trip_id":"52_818683"},{"route_id":"012","start_time":"15:40:00","start_stop_name":"SETTEMBRINI CAPOLINEA","finish_time":"16:20:00","finish_stop_name":"S.FRANCESCO","trip_id":"52_818684"},{"route_id":"012","start_time":"16:20:00","start_stop_name":"SETTEMBRINI CAPOLINEA","finish_time":"17:00:00","finish_stop_name":"S.FRANCESCO","trip_id":"52_818685"},{"route_id":"012","start_time":"17:00:00","start_stop_name":"SETTEMBRINI CAPOLINEA","finish_time":"17:41:00","finish_stop_name":"S.FRANCESCO","trip_id":"52_818686"},{"route_id":"012","start_time":"17:40:00","start_stop_name":"SETTEMBRINI CAPOLINEA","finish_time":"18:22:00","finish_stop_name":"S.FRANCESCO","trip_id":"52_818687"},{"route_id":"012","start_time":"18:20:00","start_stop_name":"SETTEMBRINI CAPOLINEA","finish_time":"19:02:00","finish_stop_name":"S.FRANCESCO","trip_id":"52_818688"},{"route_id":"012","start_time":"19:00:00","start_stop_name":"SETTEMBRINI CAPOLINEA","finish_time":"19:42:00","finish_stop_name":"S.FRANCESCO","trip_id":"52_818689"},{"route_id":"012","start_time":"19:40:00","start_stop_name":"SETTEMBRINI CAPOLINEA","finish_time":"20:22:00","finish_stop_name":"S.FRANCESCO","trip_id":"52_818690"},{"route_id":"012","start_time":"20:30:00","start_stop_name":"SETTEMBRINI CAPOLINEA","finish_time":"21:06:00","finish_stop_name":"S.FRANCESCO","trip_id":"52_818691"},{"route_id":"012","start_time":"21:00:00","start_stop_name":"SETTEMBRINI CAPOLINEA","finish_time":"21:33:00","finish_stop_name":"S.FRANCESCO","trip_id":"52_818692"},{"route_id":"012","start_time":"22:01:00","start_stop_name":"SETTEMBRINI CAPOLINEA","finish_time":"22:33:00","finish_stop_name":"S.FRANCESCO","trip_id":"52_818693"},{"route_id":"012","start_time":"06:21:00","start_stop_name":"S.FRANCESCO","finish_time":"06:47:00","finish_stop_name":"SETTEMBRINI CAPOLINEA","trip_id":"52_817776"},{"route_id":"012","start_time":"07:36:00","start_stop_name":"S.FRANCESCO","finish_time":"08:04:00","finish_stop_name":"SETTEMBRINI CAPOLINEA","trip_id":"52_817777"},{"route_id":"012","start_time":"08:19:00","start_stop_name":"S.FRANCESCO","finish_time":"08:49:00","finish_stop_name":"SETTEMBRINI CAPOLINEA","trip_id":"52_817778"},{"route_id":"012","start_time":"09:02:00","start_stop_name":"S.FRANCESCO","finish_time":"09:33:00","finish_stop_name":"SETTEMBRINI CAPOLINEA","trip_id":"52_817779"},{"route_id":"012","start_time":"09:43:00","start_stop_name":"S.FRANCESCO","finish_time":"10:14:00","finish_stop_name":"SETTEMBRINI CAPOLINEA","trip_id":"52_817780"},{"route_id":"012","start_time":"10:22:00","start_stop_name":"S.FRANCESCO","finish_time":"10:53:00","finish_stop_name":"SETTEMBRINI CAPOLINEA","trip_id":"52_816697"},{"route_id":"012","start_time":"11:02:00","start_stop_name":"S.FRANCESCO","finish_time":"11:33:00","finish_stop_name":"SETTEMBRINI CAPOLINEA","trip_id":"52_816698"},{"route_id":"012","start_time":"11:42:00","start_stop_name":"S.FRANCESCO","finish_time":"12:13:00","finish_stop_name":"SETTEMBRINI CAPOLINEA","trip_id":"52_816699"},{"route_id":"012","start_time":"12:22:00","start_stop_name":"S.FRANCESCO","finish_time":"12:53:00","finish_stop_name":"SETTEMBRINI CAPOLINEA","trip_id":"52_816700"},{"route_id":"012","start_time":"13:02:00","start_stop_name":"S.FRANCESCO","finish_time":"13:33:00","finish_stop_name":"SETTEMBRINI CAPOLINEA","trip_id":"52_816701"},{"route_id":"012","start_time":"13:41:00","start_stop_name":"S.FRANCESCO","finish_time":"14:11:00","finish_stop_name":"SETTEMBRINI CAPOLINEA","trip_id":"52_816702"},{"route_id":"012","start_time":"14:20:00","start_stop_name":"S.FRANCESCO","finish_time":"14:50:00","finish_stop_name":"SETTEMBRINI CAPOLINEA","trip_id":"52_816703"},{"route_id":"012","start_time":"15:00:00","start_stop_name":"S.FRANCESCO","finish_time":"15:30:00","finish_stop_name":"SETTEMBRINI CAPOLINEA","trip_id":"52_816704"},{"route_id":"012","start_time":"15:40:00","start_stop_name":"S.FRANCESCO","finish_time":"16:10:00","finish_stop_name":"SETTEMBRINI CAPOLINEA","trip_id":"52_816705"},{"route_id":"012","start_time":"16:20:00","start_stop_name":"S.FRANCESCO","finish_time":"16:50:00","finish_stop_name":"SETTEMBRINI CAPOLINEA","trip_id":"52_816706"},{"route_id":"012","start_time":"17:00:00","start_stop_name":"S.FRANCESCO","finish_time":"17:30:00","finish_stop_name":"SETTEMBRINI CAPOLINEA","trip_id":"52_816707"},{"route_id":"012","start_time":"17:41:00","start_stop_name":"S.FRANCESCO","finish_time":"18:12:00","finish_stop_name":"SETTEMBRINI CAPOLINEA","trip_id":"52_816708"},{"route_id":"012","start_time":"18:22:00","start_stop_name":"S.FRANCESCO","finish_time":"18:53:00","finish_stop_name":"SETTEMBRINI CAPOLINEA","trip_id":"52_816709"},{"route_id":"012","start_time":"19:02:00","start_stop_name":"S.FRANCESCO","finish_time":"19:33:00","finish_stop_name":"SETTEMBRINI CAPOLINEA","trip_id":"52_816710"},{"route_id":"012","start_time":"19:42:00","start_stop_name":"S.FRANCESCO","finish_time":"20:13:00","finish_stop_name":"SETTEMBRINI CAPOLINEA","trip_id":"52_816711"},{"route_id":"012","start_time":"20:22:00","start_stop_name":"S.FRANCESCO","finish_time":"20:52:00","finish_stop_name":"SETTEMBRINI CAPOLINEA","trip_id":"52_816712"},{"route_id":"012","start_time":"21:06:00","start_stop_name":"S.FRANCESCO","finish_time":"21:34:00","finish_stop_name":"SETTEMBRINI CAPOLINEA","trip_id":"52_816713"},{"route_id":"012","start_time":"21:33:00","start_stop_name":"S.FRANCESCO","finish_time":"22:01:00","finish_stop_name":"SETTEMBRINI CAPOLINEA","trip_id":"52_816714"},{"route_id":"012","start_time":"22:33:00","start_stop_name":"S.FRANCESCO","finish_time":"22:59:00","finish_stop_name":"SETTEMBRINI CAPOLINEA","trip_id":"52_816715"},{"route_id":"017","start_time":"07:05:00","start_stop_name":"FUORNI CAPOLINEA","finish_time":"08:07:00","finish_stop_name":"FISCIANO UNIVERSITA","trip_id":"52_817223"},{"route_id":"017","start_time":"07:20:00","start_stop_name":"FUORNI CAPOLINEA","finish_time":"08:25:00","finish_stop_name":"FISCIANO UNIVERSITA","trip_id":"52_815454"},{"route_id":"017","start_time":"07:45:00","start_stop_name":"FUORNI CAPOLINEA","finish_time":"08:51:00","finish_stop_name":"FISCIANO UNIVERSITA","trip_id":"52_815455"},{"route_id":"017","start_time":"08:15:00","start_stop_name":"FUORNI CAPOLINEA","finish_time":"09:23:00","finish_stop_name":"FISCIANO UNIVERSITA","trip_id":"52_817169"},{"route_id":"017","start_time":"09:30:00","start_stop_name":"PARCO ARBOSTELLA","finish_time":"10:28:00","finish_stop_name":"FISCIANO UNIVERSITA","trip_id":"52_815456"},{"route_id":"017","start_time":"10:30:00","start_stop_name":"PARCO ARBOSTELLA","finish_time":"11:28:00","finish_stop_name":"FISCIANO UNIVERSITA","trip_id":"52_815457"},{"route_id":"017","start_time":"11:30:00","start_stop_name":"PARCO ARBOSTELLA","finish_time":"12:28:00","finish_stop_name":"FISCIANO UNIVERSITA","trip_id":"52_815458"},{"route_id":"017","start_time":"12:30:00","start_stop_name":"PARCO ARBOSTELLA","finish_time":"13:28:00","finish_stop_name":"FISCIANO UNIVERSITA","trip_id":"52_815459"},{"route_id":"017","start_time":"13:20:00","start_stop_name":"FUORNI CAPOLINEA","finish_time":"14:28:00","finish_stop_name":"FISCIANO UNIVERSITA","trip_id":"52_815460"},{"route_id":"017","start_time":"14:20:00","start_stop_name":"FUORNI CAPOLINEA","finish_time":"15:26:00","finish_stop_name":"FISCIANO UNIVERSITA","trip_id":"52_815461"},{"route_id":"017","start_time":"15:30:00","start_stop_name":"PARCO ARBOSTELLA","finish_time":"16:23:00","finish_stop_name":"FISCIANO UNIVERSITA","trip_id":"52_815462"},{"route_id":"017","start_time":"16:30:00","start_stop_name":"PARCO ARBOSTELLA","finish_time":"17:26:00","finish_stop_name":"FISCIANO UNIVERSITA","trip_id":"52_815463"},{"route_id":"017","start_time":"17:30:00","start_stop_name":"PARCO ARBOSTELLA","finish_time":"18:27:00","finish_stop_name":"FISCIANO UNIVERSITA","trip_id":"52_815464"},{"route_id":"017","start_time":"08:15:00","start_stop_name":"FISCIANO UNIVERSITA","finish_time":"09:03:00","finish_stop_name":"PARCO ARBOSTELLA","trip_id":"52_815469"},{"route_id":"017","start_time":"08:50:00","start_stop_name":"FISCIANO UNIVERSITA","finish_time":"10:00:00","finish_stop_name":"FUORNI CAPOLINEA","trip_id":"52_815371"},{"route_id":"017","start_time":"09:15:00","start_stop_name":"FISCIANO UNIVERSITA","finish_time":"10:03:00","finish_stop_name":"PARCO ARBOSTELLA","trip_id":"52_815470"},{"route_id":"017","start_time":"10:15:00","start_stop_name":"FISCIANO UNIVERSITA","finish_time":"11:03:00","finish_stop_name":"PARCO ARBOSTELLA","trip_id":"52_815471"},{"route_id":"017","start_time":"11:15:00","start_stop_name":"FISCIANO UNIVERSITA","finish_time":"12:03:00","finish_stop_name":"PARCO ARBOSTELLA","trip_id":"52_815472"},{"route_id":"017","start_time":"12:05:00","start_stop_name":"FISCIANO UNIVERSITA","finish_time":"13:07:00","finish_stop_name":"FUORNI CAPOLINEA","trip_id":"52_815105"},{"route_id":"017","start_time":"13:15:00","start_stop_name":"FISCIANO UNIVERSITA","finish_time":"14:17:00","finish_stop_name":"FUORNI CAPOLINEA","trip_id":"52_815473"},{"route_id":"017","start_time":"14:15:00","start_stop_name":"FISCIANO UNIVERSITA","finish_time":"15:03:00","finish_stop_name":"PARCO ARBOSTELLA","trip_id":"52_817607"},{"route_id":"017","start_time":"15:15:00","start_stop_name":"FISCIANO UNIVERSITA","finish_time":"16:03:00","finish_stop_name":"PARCO ARBOSTELLA","trip_id":"52_817177"},{"route_id":"017","start_time":"16:15:00","start_stop_name":"FISCIANO UNIVERSITA","finish_time":"17:03:00","finish_stop_name":"PARCO ARBOSTELLA","trip_id":"52_815474"},{"route_id":"017","start_time":"18:15:00","start_stop_name":"FISCIANO UNIVERSITA","finish_time":"19:18:00","finish_stop_name":"FUORNI CAPOLINEA","trip_id":"52_815475"},{"route_id":"017","start_time":"18:35:00","start_stop_name":"FISCIANO UNIVERSITA","finish_time":"19:37:00","finish_stop_name":"FUORNI CAPOLINEA","trip_id":"52_817178"},{"route_id":"017","start_time":"19:25:00","start_stop_name":"FISCIANO UNIVERSITA","finish_time":"20:27:00","finish_stop_name":"FUORNI CAPOLINEA","trip_id":"52_815476"},{"route_id":"017","start_time":"20:15:00","start_stop_name":"FISCIANO UNIVERSITA","finish_time":"21:14:00","finish_stop_name":"FUORNI CAPOLINEA","trip_id":"52_817206"},{"route_id":"027","start_time":"07:05:00","start_stop_name":"FUORNI CAPOLINEA","finish_time":"08:04:00","finish_stop_name":"FISCIANO UNIVERSITA","trip_id":"52_815465"},{"route_id":"027","start_time":"07:50:00","start_stop_name":"FUORNI CAPOLINEA","finish_time":"08:55:00","finish_stop_name":"FISCIANO UNIVERSITA","trip_id":"52_817608"},{"route_id":"027","start_time":"09:00:00","start_stop_name":"PARCO ARBOSTELLA","finish_time":"09:55:00","finish_stop_name":"FISCIANO UNIVERSITA","trip_id":"52_817170"},{"route_id":"027","start_time":"10:00:00","start_stop_name":"PARCO ARBOSTELLA","finish_time":"10:55:00","finish_stop_name":"FISCIANO UNIVERSITA","trip_id":"52_817171"},{"route_id":"027","start_time":"11:00:00","start_stop_name":"PARCO ARBOSTELLA","finish_time":"11:55:00","finish_stop_name":"FISCIANO UNIVERSITA","trip_id":"52_817172"},{"route_id":"027","start_time":"12:00:00","start_stop_name":"PARCO ARBOSTELLA","finish_time":"12:55:00","finish_stop_name":"FISCIANO UNIVERSITA","trip_id":"52_817173"},{"route_id":"027","start_time":"13:00:00","start_stop_name":"PARCO ARBOSTELLA","finish_time":"13:54:00","finish_stop_name":"FISCIANO UNIVERSITA","trip_id":"52_817174"},{"route_id":"027","start_time":"13:50:00","start_stop_name":"FUORNI CAPOLINEA","finish_time":"14:53:00","finish_stop_name":"FISCIANO UNIVERSITA","trip_id":"52_817175"},{"route_id":"027","start_time":"15:00:00","start_stop_name":"PARCO ARBOSTELLA","finish_time":"15:50:00","finish_stop_name":"FISCIANO UNIVERSITA","trip_id":"52_815466"},{"route_id":"027","start_time":"16:00:00","start_stop_name":"PARCO ARBOSTELLA","finish_time":"16:51:00","finish_stop_name":"FISCIANO UNIVERSITA","trip_id":"52_815467"},{"route_id":"027","start_time":"17:00:00","start_stop_name":"PARCO ARBOSTELLA","finish_time":"17:55:00","finish_stop_name":"FISCIANO UNIVERSITA","trip_id":"52_815468"},{"route_id":"027","start_time":"18:05:00","start_stop_name":"PARCO ARBOSTELLA","finish_time":"19:01:00","finish_stop_name":"FISCIANO UNIVERSITA","trip_id":"52_817176"},{"route_id":"027","start_time":"08:05:00","start_stop_name":"FISCIANO UNIVERSITA","finish_time":"08:50:00","finish_stop_name":"PARCO ARBOSTELLA","trip_id":"52_817600"},{"route_id":"027","start_time":"08:45:00","start_stop_name":"FISCIANO UNIVERSITA","finish_time":"09:19:00","finish_stop_name":"SALERNO STAZIONE","trip_id":"52_819403"},{"route_id":"027","start_time":"08:55:00","start_stop_name":"FISCIANO UNIVERSITA","finish_time":"09:40:00","finish_stop_name":"PARCO ARBOSTELLA","trip_id":"52_817601"},{"route_id":"027","start_time":"09:20:00","start_stop_name":"FISCIANO UNIVERSITA","finish_time":"10:25:00","finish_stop_name":"FUORNI CAPOLINEA","trip_id":"52_815374"},{"route_id":"027","start_time":"09:55:00","start_stop_name":"FISCIANO UNIVERSITA","finish_time":"10:40:00","finish_stop_name":"PARCO ARBOSTELLA","trip_id":"52_817602"},{"route_id":"027","start_time":"10:55:00","start_stop_name":"FISCIANO UNIVERSITA","finish_time":"11:39:00","finish_stop_name":"PARCO ARBOSTELLA","trip_id":"52_817179"},{"route_id":"027","start_time":"11:55:00","start_stop_name":"FISCIANO UNIVERSITA","finish_time":"12:39:00","finish_stop_name":"PARCO ARBOSTELLA","trip_id":"52_817180"},{"route_id":"027","start_time":"12:55:00","start_stop_name":"FISCIANO UNIVERSITA","finish_time":"13:50:00","finish_stop_name":"FUORNI CAPOLINEA","trip_id":"52_817181"},{"route_id":"027","start_time":"13:55:00","start_stop_name":"FISCIANO UNIVERSITA","finish_time":"14:39:00","finish_stop_name":"PARCO ARBOSTELLA","trip_id":"52_817182"},{"route_id":"027","start_time":"14:55:00","start_stop_name":"FISCIANO UNIVERSITA","finish_time":"15:39:00","finish_stop_name":"PARCO ARBOSTELLA","trip_id":"52_817603"},{"route_id":"027","start_time":"15:55:00","start_stop_name":"FISCIANO UNIVERSITA","finish_time":"16:40:00","finish_stop_name":"PARCO ARBOSTELLA","trip_id":"52_817604"},{"route_id":"027","start_time":"16:55:00","start_stop_name":"FISCIANO UNIVERSITA","finish_time":"17:40:00","finish_stop_name":"PARCO ARBOSTELLA","trip_id":"52_817605"},{"route_id":"027","start_time":"17:55:00","start_stop_name":"FISCIANO UNIVERSITA","finish_time":"18:55:00","finish_stop_name":"FUORNI CAPOLINEA","trip_id":"52_817606"},{"route_id":"027","start_time":"19:05:00","start_stop_name":"FISCIANO UNIVERSITA","finish_time":"20:03:00","finish_stop_name":"FUORNI CAPOLINEA","trip_id":"52_817224"},{"route_id":"007","start_time":"09:15:00","start_stop_name":"VINCIPROVA","finish_time":"09:54:00","finish_stop_name":"FISCIANO UNIVERSITA","trip_id":"52_830379"},{"route_id":"007","start_time":"10:15:00","start_stop_name":"VINCIPROVA","finish_time":"10:54:00","finish_stop_name":"FISCIANO UNIVERSITA","trip_id":"52_830381"},{"route_id":"007","start_time":"11:15:00","start_stop_name":"VINCIPROVA","finish_time":"11:54:00","finish_stop_name":"FISCIANO UNIVERSITA","trip_id":"52_830383"},{"route_id":"007","start_time":"12:15:00","start_stop_name":"VINCIPROVA","finish_time":"12:54:00","finish_stop_name":"FISCIANO UNIVERSITA","trip_id":"52_830385"},{"route_id":"007","start_time":"13:15:00","start_stop_name":"VINCIPROVA","finish_time":"13:54:00","finish_stop_name":"FISCIANO UNIVERSITA","trip_id":"52_830376"},{"route_id":"007","start_time":"14:15:00","start_stop_name":"VINCIPROVA","finish_time":"14:53:00","finish_stop_name":"FISCIANO UNIVERSITA","trip_id":"52_830389"},{"route_id":"007","start_time":"15:15:00","start_stop_name":"VINCIPROVA","finish_time":"15:53:00","finish_stop_name":"FISCIANO UNIVERSITA","trip_id":"52_830393"},{"route_id":"007","start_time":"16:15:00","start_stop_name":"VINCIPROVA","finish_time":"16:53:00","finish_stop_name":"FISCIANO UNIVERSITA","trip_id":"52_830396"},{"route_id":"007","start_time":"16:30:00","start_stop_name":"VINCIPROVA","finish_time":"17:08:00","finish_stop_name":"FISCIANO UNIVERSITA","trip_id":"52_830397"},{"route_id":"007","start_time":"17:15:00","start_stop_name":"VINCIPROVA","finish_time":"17:53:00","finish_stop_name":"FISCIANO UNIVERSITA","trip_id":"52_830400"},{"route_id":"007","start_time":"18:20:00","start_stop_name":"VINCIPROVA","finish_time":"18:58:00","finish_stop_name":"FISCIANO UNIVERSITA","trip_id":"52_830402"},{"route_id":"007","start_time":"19:00:00","start_stop_name":"VINCIPROVA","finish_time":"19:38:00","finish_stop_name":"FISCIANO UNIVERSITA","trip_id":"52_830403"},{"route_id":"007","start_time":"08:35:00","start_stop_name":"FISCIANO UNIVERSITA","finish_time":"09:15:00","finish_stop_name":"VINCIPROVA","trip_id":"52_830408"},{"route_id":"007","start_time":"09:35:00","start_stop_name":"FISCIANO UNIVERSITA","finish_time":"10:15:00","finish_stop_name":"VINCIPROVA","trip_id":"52_830413"},{"route_id":"007","start_time":"10:35:00","start_stop_name":"FISCIANO UNIVERSITA","finish_time":"11:15:00","finish_stop_name":"VINCIPROVA","trip_id":"52_830419"},{"route_id":"007","start_time":"11:35:00","start_stop_name":"FISCIANO UNIVERSITA","finish_time":"12:15:00","finish_stop_name":"VINCIPROVA","trip_id":"52_830424"},{"route_id":"007","start_time":"12:35:00","start_stop_name":"FISCIANO UNIVERSITA","finish_time":"13:15:00","finish_stop_name":"VINCIPROVA","trip_id":"52_830429"},{"route_id":"007","start_time":"13:35:00","start_stop_name":"FISCIANO UNIVERSITA","finish_time":"14:15:00","finish_stop_name":"VINCIPROVA","trip_id":"52_830432"},{"route_id":"007","start_time":"14:35:00","start_stop_name":"FISCIANO UNIVERSITA","finish_time":"15:15:00","finish_stop_name":"VINCIPROVA","trip_id":"52_830435"},{"route_id":"007","start_time":"15:35:00","start_stop_name":"FISCIANO UNIVERSITA","finish_time":"16:15:00","finish_stop_name":"VINCIPROVA","trip_id":"52_830439"},{"route_id":"007","start_time":"16:35:00","start_stop_name":"FISCIANO UNIVERSITA","finish_time":"17:15:00","finish_stop_name":"VINCIPROVA","trip_id":"52_830442"},{"route_id":"007","start_time":"17:15:00","start_stop_name":"FISCIANO UNIVERSITA","finish_time":"17:55:00","finish_stop_name":"VINCIPROVA","trip_id":"52_830445"},{"route_id":"007","start_time":"17:35:00","start_stop_name":"FISCIANO UNIVERSITA","finish_time":"18:15:00","finish_stop_name":"VINCIPROVA","trip_id":"52_830406"},{"route_id":"019","start_time":"07:15:00","start_stop_name":"LIGEA  CAPOLINEA","finish_time":"07:45:00","finish_stop_name":"CROCE CAPOLINEA","trip_id":"52_816716"},{"route_id":"019","start_time":"09:30:00","start_stop_name":"LIGEA  CAPOLINEA","finish_time":"10:05:00","finish_stop_name":"CROCE CAPOLINEA","trip_id":"52_816717"},{"route_id":"019","start_time":"11:30:00","start_stop_name":"LIGEA  CAPOLINEA","finish_time":"12:05:00","finish_stop_name":"CROCE CAPOLINEA","trip_id":"52_816718"},{"route_id":"019","start_time":"13:40:00","start_stop_name":"LIGEA  CAPOLINEA","finish_time":"14:11:00","finish_stop_name":"CROCE CAPOLINEA","trip_id":"52_816719"},{"route_id":"019","start_time":"14:50:00","start_stop_name":"LIGEA  CAPOLINEA","finish_time":"15:19:00","finish_stop_name":"CROCE CAPOLINEA","trip_id":"52_816720"},{"route_id":"019","start_time":"15:30:00","start_stop_name":"LIGEA  CAPOLINEA","finish_time":"15:59:00","finish_stop_name":"CROCE CAPOLINEA","trip_id":"52_816721"},{"route_id":"019","start_time":"17:30:00","start_stop_name":"LIGEA  CAPOLINEA","finish_time":"18:00:00","finish_stop_name":"CROCE CAPOLINEA","trip_id":"52_816722"},{"route_id":"019","start_time":"19:00:00","start_stop_name":"LIGEA  CAPOLINEA","finish_time":"19:30:00","finish_stop_name":"CROCE CAPOLINEA","trip_id":"52_816723"},{"route_id":"019","start_time":"20:30:00","start_stop_name":"LIGEA  CAPOLINEA","finish_time":"20:59:00","finish_stop_name":"CROCE CAPOLINEA","trip_id":"52_816724"},{"route_id":"019","start_time":"07:45:00","start_stop_name":"CROCE CAPOLINEA","finish_time":"08:23:00","finish_stop_name":"LIGEA  CAPOLINEA","trip_id":"52_816725"},{"route_id":"019","start_time":"10:10:00","start_stop_name":"CROCE CAPOLINEA","finish_time":"10:42:00","finish_stop_name":"LIGEA  CAPOLINEA","trip_id":"52_816726"},{"route_id":"019","start_time":"12:05:00","start_stop_name":"CROCE CAPOLINEA","finish_time":"12:35:00","finish_stop_name":"LIGEA  CAPOLINEA","trip_id":"52_816727"},{"route_id":"019","start_time":"14:15:00","start_stop_name":"CROCE CAPOLINEA","finish_time":"14:44:00","finish_stop_name":"LIGEA  CAPOLINEA","trip_id":"52_816728"},{"route_id":"019","start_time":"15:25:00","start_stop_name":"CROCE CAPOLINEA","finish_time":"15:54:00","finish_stop_name":"LIGEA  CAPOLINEA","trip_id":"52_816729"},{"route_id":"019","start_time":"16:05:00","start_stop_name":"CROCE CAPOLINEA","finish_time":"16:35:00","finish_stop_name":"LIGEA  CAPOLINEA","trip_id":"52_816730"},{"route_id":"019","start_time":"18:05:00","start_stop_name":"CROCE CAPOLINEA","finish_time":"18:35:00","finish_stop_name":"LIGEA  CAPOLINEA","trip_id":"52_816731"},{"route_id":"019","start_time":"19:35:00","start_stop_name":"CROCE CAPOLINEA","finish_time":"20:05:00","finish_stop_name":"LIGEA  CAPOLINEA","trip_id":"52_816732"},{"route_id":"019","start_time":"21:30:00","start_stop_name":"CROCE CAPOLINEA","finish_time":"21:58:00","finish_stop_name":"LIGEA  CAPOLINEA","trip_id":"52_816733"},{"route_id":"039","start_time":"07:15:00","start_stop_name":"VINCIPROVA","finish_time":"07:41:00","finish_stop_name":"SERIPANDO (CAP.)","trip_id":"52_819472"},{"route_id":"039","start_time":"08:10:00","start_stop_name":"VINCIPROVA","finish_time":"08:39:00","finish_stop_name":"SERIPANDO (CAP.)","trip_id":"52_819459"},{"route_id":"039","start_time":"09:20:00","start_stop_name":"VINCIPROVA","finish_time":"09:49:00","finish_stop_name":"SERIPANDO (CAP.)","trip_id":"52_819460"},{"route_id":"039","start_time":"10:30:00","start_stop_name":"VINCIPROVA","finish_time":"10:59:00","finish_stop_name":"SERIPANDO (CAP.)","trip_id":"52_819461"},{"route_id":"039","start_time":"11:40:00","start_stop_name":"VINCIPROVA","finish_time":"12:09:00","finish_stop_name":"SERIPANDO (CAP.)","trip_id":"52_819462"},{"route_id":"039","start_time":"12:50:00","start_stop_name":"VINCIPROVA","finish_time":"13:19:00","finish_stop_name":"SERIPANDO (CAP.)","trip_id":"52_819463"},{"route_id":"039","start_time":"14:00:00","start_stop_name":"VINCIPROVA","finish_time":"14:27:00","finish_stop_name":"SERIPANDO (CAP.)","trip_id":"52_819464"},{"route_id":"039","start_time":"15:10:00","start_stop_name":"VINCIPROVA","finish_time":"15:37:00","finish_stop_name":"SERIPANDO (CAP.)","trip_id":"52_819465"},{"route_id":"039","start_time":"16:20:00","start_stop_name":"VINCIPROVA","finish_time":"16:47:00","finish_stop_name":"SERIPANDO (CAP.)","trip_id":"52_819466"},{"route_id":"039","start_time":"17:30:00","start_stop_name":"VINCIPROVA","finish_time":"17:58:00","finish_stop_name":"SERIPANDO (CAP.)","trip_id":"52_819467"},{"route_id":"039","start_time":"18:40:00","start_stop_name":"VINCIPROVA","finish_time":"19:08:00","finish_stop_name":"SERIPANDO (CAP.)","trip_id":"52_819468"},{"route_id":"039","start_time":"19:50:00","start_stop_name":"VINCIPROVA","finish_time":"20:18:00","finish_stop_name":"SERIPANDO (CAP.)","trip_id":"52_819469"},{"route_id":"039","start_time":"21:00:00","start_stop_name":"VINCIPROVA","finish_time":"21:25:00","finish_stop_name":"SERIPANDO (CAP.)","trip_id":"52_819470"},{"route_id":"039","start_time":"21:50:00","start_stop_name":"VINCIPROVA","finish_time":"22:15:00","finish_stop_name":"SERIPANDO (CAP.)","trip_id":"52_819471"},{"route_id":"039","start_time":"07:45:00","start_stop_name":"SERIPANDO (CAP.)","finish_time":"08:05:00","finish_stop_name":"VINCIPROVA","trip_id":"52_819458"},{"route_id":"039","start_time":"08:40:00","start_stop_name":"SERIPANDO (CAP.)","finish_time":"09:05:00","finish_stop_name":"VINCIPROVA","trip_id":"52_819473"},{"route_id":"039","start_time":"09:50:00","start_stop_name":"SERIPANDO (CAP.)","finish_time":"10:15:00","finish_stop_name":"VINCIPROVA","trip_id":"52_819474"},{"route_id":"039","start_time":"11:00:00","start_stop_name":"SERIPANDO (CAP.)","finish_time":"11:25:00","finish_stop_name":"VINCIPROVA","trip_id":"52_819475"},{"route_id":"039","start_time":"12:10:00","start_stop_name":"SERIPANDO (CAP.)","finish_time":"12:35:00","finish_stop_name":"VINCIPROVA","trip_id":"52_819476"},{"route_id":"039","start_time":"13:20:00","start_stop_name":"SERIPANDO (CAP.)","finish_time":"13:45:00","finish_stop_name":"VINCIPROVA","trip_id":"52_819477"},{"route_id":"039","start_time":"14:30:00","start_stop_name":"SERIPANDO (CAP.)","finish_time":"14:55:00","finish_stop_name":"VINCIPROVA","trip_id":"52_819478"},{"route_id":"039","start_time":"15:40:00","start_stop_name":"SERIPANDO (CAP.)","finish_time":"16:05:00","finish_stop_name":"VINCIPROVA","trip_id":"52_819479"},{"route_id":"039","start_time":"16:50:00","start_stop_name":"SERIPANDO (CAP.)","finish_time":"17:15:00","finish_stop_name":"VINCIPROVA","trip_id":"52_819480"},{"route_id":"039","start_time":"18:00:00","start_stop_name":"SERIPANDO (CAP.)","finish_time":"18:25:00","finish_stop_name":"VINCIPROVA","trip_id":"52_819481"},{"route_id":"039","start_time":"19:10:00","start_stop_name":"SERIPANDO (CAP.)","finish_time":"19:35:00","finish_stop_name":"VINCIPROVA","trip_id":"52_819482"},{"route_id":"039","start_time":"20:20:00","start_stop_name":"SERIPANDO (CAP.)","finish_time":"20:45:00","finish_stop_name":"VINCIPROVA","trip_id":"52_819483"},{"route_id":"039","start_time":"21:30:00","start_stop_name":"SERIPANDO (CAP.)","finish_time":"21:50:00","finish_stop_name":"VINCIPROVA","trip_id":"52_819484"},{"route_id":"039","start_time":"22:15:00","start_stop_name":"SERIPANDO (CAP.)","finish_time":"22:35:00","finish_stop_name":"VINCIPROVA","trip_id":"52_819485"},{"route_id":"050","start_time":"06:10:00","start_stop_name":"POMPEI MAZZINI","finish_time":"07:15:00","finish_stop_name":"VINCIPROVA","trip_id":"52_826467"},{"route_id":"050","start_time":"07:05:00","start_stop_name":"S. EGIDIO M.A. (MERC. ORTOFRUTTICOLO)","finish_time":"08:30:00","finish_stop_name":"CONCORDIA","trip_id":"52_826492"},{"route_id":"050","start_time":"07:10:00","start_stop_name":"POMPEI MAZZINI","finish_time":"08:25:00","finish_stop_name":"VINCIPROVA","trip_id":"52_826468"},{"route_id":"050","start_time":"07:10:00","start_stop_name":"ANGRI CROCIFISSO","finish_time":"07:51:00","finish_stop_name":"VINCIPROVA","trip_id":"52_818557"},{"route_id":"050","start_time":"07:30:00","start_stop_name":"POMPEI MAZZINI","finish_time":"08:47:00","finish_stop_name":"VINCIPROVA","trip_id":"52_826469"},{"route_id":"050","start_time":"08:45:00","start_stop_name":"POMPEI MAZZINI","finish_time":"10:01:00","finish_stop_name":"VINCIPROVA","trip_id":"52_826458"},{"route_id":"050","start_time":"09:45:00","start_stop_name":"POMPEI MAZZINI","finish_time":"10:51:00","finish_stop_name":"VINCIPROVA","trip_id":"52_826459"},{"route_id":"050","start_time":"10:25:00","start_stop_name":"POMPEI MAZZINI","finish_time":"11:31:00","finish_stop_name":"VINCIPROVA","trip_id":"52_826460"},{"route_id":"050","start_time":"11:40:00","start_stop_name":"POMPEI MAZZINI","finish_time":"12:45:00","finish_stop_name":"VINCIPROVA","trip_id":"52_826461"},{"route_id":"050","start_time":"12:25:00","start_stop_name":"POMPEI MAZZINI","finish_time":"13:31:00","finish_stop_name":"VINCIPROVA","trip_id":"52_826462"},{"route_id":"050","start_time":"13:10:00","start_stop_name":"POMPEI MAZZINI","finish_time":"14:22:00","finish_stop_name":"VINCIPROVA","trip_id":"52_826470"},{"route_id":"050","start_time":"14:20:00","start_stop_name":"POMPEI MAZZINI","finish_time":"15:23:00","finish_stop_name":"VINCIPROVA","trip_id":"52_826463"},{"route_id":"050","start_time":"15:05:00","start_stop_name":"POMPEI MAZZINI","finish_time":"16:06:00","finish_stop_name":"VINCIPROVA","trip_id":"52_826464"},{"route_id":"050","start_time":"16:00:00","start_stop_name":"POMPEI MAZZINI","finish_time":"17:13:00","finish_stop_name":"VINCIPROVA","trip_id":"52_826471"},{"route_id":"050","start_time":"17:05:00","start_stop_name":"POMPEI MAZZINI","finish_time":"18:17:00","finish_stop_name":"VINCIPROVA","trip_id":"52_826465"},{"route_id":"050","start_time":"17:55:00","start_stop_name":"POMPEI MAZZINI","finish_time":"19:17:00","finish_stop_name":"VINCIPROVA","trip_id":"52_826472"},{"route_id":"050","start_time":"18:55:00","start_stop_name":"POMPEI MAZZINI","finish_time":"20:07:00","finish_stop_name":"VINCIPROVA","trip_id":"52_826466"},{"route_id":"050","start_time":"20:00:00","start_stop_name":"POMPEI MAZZINI","finish_time":"21:18:00","finish_stop_name":"VINCIPROVA","trip_id":"52_826473"},{"route_id":"050","start_time":"06:05:00","start_stop_name":"VINCIPROVA","finish_time":"07:10:00","finish_stop_name":"POMPEI MAZZINI","trip_id":"52_826474"},{"route_id":"050","start_time":"07:20:00","start_stop_name":"VINCIPROVA","finish_time":"08:35:00","finish_stop_name":"POMPEI MAZZINI","trip_id":"52_826479"},{"route_id":"050","start_time":"08:20:00","start_stop_name":"VINCIPROVA","finish_time":"09:38:00","finish_stop_name":"POMPEI MAZZINI","trip_id":"52_826475"},{"route_id":"050","start_time":"08:35:00","start_stop_name":"VINCIPROVA","finish_time":"09:22:00","finish_stop_name":"ANGRI CROCIFISSO","trip_id":"52_818562"},{"route_id":"050","start_time":"09:00:00","start_stop_name":"VINCIPROVA","finish_time":"10:18:00","finish_stop_name":"POMPEI MAZZINI","trip_id":"52_826476"},{"route_id":"050","start_time":"10:15:00","start_stop_name":"VINCIPROVA","finish_time":"11:33:00","finish_stop_name":"POMPEI MAZZINI","trip_id":"52_826477"},{"route_id":"050","start_time":"11:10:00","start_stop_name":"VINCIPROVA","finish_time":"12:25:00","finish_stop_name":"POMPEI MAZZINI","trip_id":"52_826478"},{"route_id":"050","start_time":"11:50:00","start_stop_name":"VINCIPROVA","finish_time":"13:07:00","finish_stop_name":"POMPEI MAZZINI","trip_id":"52_826480"},{"route_id":"050","start_time":"12:55:00","start_stop_name":"VINCIPROVA","finish_time":"14:08:00","finish_stop_name":"POMPEI MAZZINI","trip_id":"52_826481"},{"route_id":"050","start_time":"13:45:00","start_stop_name":"VINCIPROVA","finish_time":"14:56:00","finish_stop_name":"POMPEI MAZZINI","trip_id":"52_826482"},{"route_id":"050","start_time":"14:35:00","start_stop_name":"VINCIPROVA","finish_time":"15:46:00","finish_stop_name":"POMPEI MAZZINI","trip_id":"52_826483"},{"route_id":"050","start_time":"15:40:00","start_stop_name":"VINCIPROVA","finish_time":"16:51:00","finish_stop_name":"POMPEI MAZZINI","trip_id":"52_826484"},{"route_id":"050","start_time":"16:30:00","start_stop_name":"VINCIPROVA","finish_time":"17:46:00","finish_stop_name":"POMPEI MAZZINI","trip_id":"52_826485"},{"route_id":"050","start_time":"17:30:00","start_stop_name":"VINCIPROVA","finish_time":"18:55:00","finish_stop_name":"POMPEI MAZZINI","trip_id":"52_826486"},{"route_id":"050","start_time":"18:35:00","start_stop_name":"VINCIPROVA","finish_time":"19:54:00","finish_stop_name":"POMPEI MAZZINI","trip_id":"52_826487"},{"route_id":"050","start_time":"19:40:00","start_stop_name":"VINCIPROVA","finish_time":"21:03:00","finish_stop_name":"POMPEI MAZZINI","trip_id":"52_826488"},{"route_id":"050","start_time":"20:40:00","start_stop_name":"VINCIPROVA","finish_time":"21:50:00","finish_stop_name":"POMPEI MAZZINI","trip_id":"52_826489"},{"route_id":"050","start_time":"21:30:00","start_stop_name":"VINCIPROVA","finish_time":"22:45:00","finish_stop_name":"POMPEI MAZZINI","trip_id":"52_826490"},{"route_id":"119","start_time":"07:05:00","start_stop_name":"SERRE VITTORIO VENETO","finish_time":"09:40:00","finish_stop_name":"AEROPORTO CAPODICHINO","trip_id":"52_819389"},{"route_id":"119","start_time":"14:10:00","start_stop_name":"SERRE VITTORIO VENETO","finish_time":"16:30:00","finish_stop_name":"AEROPORTO CAPODICHINO","trip_id":"52_819390"},{"route_id":"119","start_time":"15:10:00","start_stop_name":"SERRE VITTORIO VENETO","finish_time":"17:30:00","finish_stop_name":"AEROPORTO CAPODICHINO","trip_id":"52_819391"},{"route_id":"119","start_time":"11:45:00","start_stop_name":"AEROPORTO CAPODICHINO","finish_time":"14:10:00","finish_stop_name":"SERRE VITTORIO VENETO","trip_id":"52_817589"},{"route_id":"119","start_time":"17:30:00","start_stop_name":"AEROPORTO CAPODICHINO","finish_time":"19:50:00","finish_stop_name":"SERRE VITTORIO VENETO","trip_id":"52_817590"},{"route_id":"119","start_time":"19:00:00","start_stop_name":"AEROPORTO CAPODICHINO","finish_time":"21:10:00","finish_stop_name":"SERRE VITTORIO VENETO","trip_id":"52_818284"}],"length":577}